Workbook
Name UPDATE: 'Data Sheet'!$E$1

Sheet FINANCIAL

Sheet HISTORICAL FC
B2: ="HISTORICAL FINANCIAL STATEMENT- "&'Data Sheet'!B1 -> HISTORICAL FINANCIAL STATEMENT- RELIANCE INDUSTRIES LTD
B3: YEARS | C3: ='Data Sheet'!B16 -> 42460 | D3: ='Data Sheet'!C16 -> 42825 | E3: ='Data Sheet'!D16 -> 43190 | F3: ='Data Sheet'!E16 -> 43555 | G3: ='Data Sheet'!F16 -> 43921 | H3: ='Data Sheet'!G16 -> 44286 | I3: ='Data Sheet'!H16 -> 44651 | J3: ='Data Sheet'!I16 -> 45016 | ... L3: ='Data Sheet'!K16 -> 45747 | M3: LTM
A5: # | B5: INCOME STATEMENT
B6: SALES | C6: ='Data Sheet'!B17 -> 272583 | D6: =IFERROR('Data Sheet'!C17,0) -> 303954 | E6: =IFERROR('Data Sheet'!D17,0) -> 390823 | F6: =IFERROR('Data Sheet'!E17,0) -> 568337 | G6: =IFERROR('Data Sheet'!F17,0) -> 596679 | H6: =IFERROR('Data Sheet'!G17,0) -> 466307 | I6: =IFERROR('Data Sheet'!H17,0) -> 694673 | J6: =IFERROR('Data Sheet'!I17,0) -> 876396 | K6: =IFERROR('Data Sheet'!J17,0) -> 899041 | L6: =IFERROR('Data Sheet'!K17,0) -> 962820 | M6: =IFERROR(SUM('Data Sheet'!H42:K42),0) -> 1024548
B7: SALES GROWTH | D7: =D6/C6-1 -> 0.11508788 | E7: =E6/D6-1 -> 0.28579654 | F7: =F6/E6-1 -> 0.45420561 | G7: =G6/F6-1 -> 0.0498683 | H7: =H6/G6-1 -> -0.21849604 | I7: =I6/H6-1 -> 0.48973316 | J7: =J6/I6-1 -> 0.26159502 | K7: =K6/J6-1 -> 0.025838776 | ... M7: =M6/L6-1 -> 0.064111672
B9: COGS | C9: =IFERROR(SUM('Data Sheet'!B18,'Data Sheet'!B20,'Data Sheet'!B21,'Data Sheet'!B22)-1*'Data Sheet'!B19,0) -> 215234 | D9: =IFERROR(SUM('Data Sheet'!C18,'Data Sheet'!C20,'Data Sheet'!C21,'Data Sheet'!C22)-1*'Data Sheet'!C19,0) -> 241848 | E9: =IFERROR(SUM('Data Sheet'!D18,'Data Sheet'!D20,'Data Sheet'!D21,'Data Sheet'!D22)-1*'Data Sheet'!D19,0) -> 301249 | F9: =IFERROR(SUM('Data Sheet'!E18,'Data Sheet'!E20,'Data Sheet'!E21,'Data Sheet'!E22)-1*'Data Sheet'!E19,0) -> 436202 | G9: =IFERROR(SUM('Data Sheet'!F18,'Data Sheet'!F20,'Data Sheet'!F21,'Data Sheet'!F22)-1*'Data Sheet'!F19,0) -> 445847 | H9: =IFERROR(SUM('Data Sheet'!G18,'Data Sheet'!G20,'Data Sheet'!G21,'Data Sheet'!G22)-1*'Data Sheet'!G19,0) -> 328419 | I9: =IFERROR(SUM('Data Sheet'!H18,'Data Sheet'!H20,'Data Sheet'!H21,'Data Sheet'!H22)-1*'Data Sheet'!H19,0) -> 521826 | J9: =IFERROR(SUM('Data Sheet'!I18,'Data Sheet'!I20,'Data Sheet'!I21,'Data Sheet'!I22)-1*'Data Sheet'!I19,0) -> 658075 | ... L9: =IFERROR(SUM('Data Sheet'!K18,'Data Sheet'!K20,'Data Sheet'!K21,'Data Sheet'!K22)-1*'Data Sheet'!K19,0) -> 700429 | M9: =IFERROR(SUM('Data Sheet'!H43:K43),0) -> 845908
B10: COGS %OF SALES | C10: =C9/C6 -> 0.78960904 | D10: =D9/D6 -> 0.79567303 | E10: =E9/E6 -> 0.77080673 | F10: =F9/F6 -> 0.7675059 | G10: =G9/G6 -> 0.74721416 | H10: =H9/H6 -> 0.70429781 | I10: =I9/I6 -> 0.75118221 | J10: =J9/J6 -> 0.75088773 | ... M10: =M9/M6 -> 0.82564018
B12: GROSS PROFIT | C12: =C6-C9 -> 57349 | D12: =D6-D9 -> 62106 | E12: =E6-E9 -> 89574 | F12: =F6-F9 -> 132135 | G12: =G6-G9 -> 150832 | H12: =H6-H9 -> 137888 | I12: =I6-I9 -> 172847 | J12: =J6-J9 -> 218321 | ... M12: =M6-M9 -> 178640
B13: GROSS MARGIN | C13: =C12/C6 -> 0.21039096 | D13: =D12/D6 -> 0.20432697 | E13: =E12/E6 -> 0.22919327 | F13: =F12/F6 -> 0.2324941 | G13: =G12/G6 -> 0.25278584 | H13: =H12/H6 -> 0.29570219 | I13: =I12/I6 -> 0.24881779 | J13: =J12/J6 -> 0.24911227 | ... M13: =M12/M6 -> 0.17435982
B15: SELLING AND GENERAL EXPENSES | C15: =IFERROR(SUM('Data Sheet'!B23,'Data Sheet'!B24),0) -> 15568 | D15: =IFERROR(SUM('Data Sheet'!C23,'Data Sheet'!C24),0) -> 15799 | E15: =IFERROR(SUM('Data Sheet'!D23,'Data Sheet'!D24),0) -> 25259 | F15: =IFERROR(SUM('Data Sheet'!E23,'Data Sheet'!E24),0) -> 47885 | G15: =IFERROR(SUM('Data Sheet'!F23,'Data Sheet'!F24),0) -> 61566 | H15: =IFERROR(SUM('Data Sheet'!G23,'Data Sheet'!G24),0) -> 57098 | I15: =IFERROR(SUM('Data Sheet'!H23,'Data Sheet'!H24),0) -> 64266 | J15: =IFERROR(SUM('Data Sheet'!I23,'Data Sheet'!I24),0) -> 76003 | ... L15: =IFERROR(SUM('Data Sheet'!K23,'Data Sheet'!K24),0) -> 96793
B16: SELLING AND GENERAL EXPENSES % OF SALES | C16: =C15/C6 -> 0.057112879 | D16: =D15/D6 -> 0.05197826 | E16: =E15/E6 -> 0.06463028 | F16: =F15/F6 -> 0.084254588 | G16: =G15/G6 -> 0.10318111 | H16: =H15/H6 -> 0.12244723 | I16: =I15/I6 -> 0.092512592 | J16: =J15/J6 -> 0.086722212 | ... M16: =M15/M6 -> 0
B18: EBITDA | C18: =C12-C15 -> 41781 | D18: =D12-D15 -> 46307 | E18: =E12-E15 -> 64315 | F18: =F12-F15 -> 84250 | G18: =G12-G15 -> 89266 | H18: =H12-H15 -> 80790 | I18: =I12-I15 -> 108581 | J18: =J12-J15 -> 142318 | ... M18: =M12-M15 -> 178640
B19: EBITDA MARGIN | C19: =C18/C6 -> 0.15327808 | D19: =D18/D6 -> 0.15234871 | E19: =E18/E6 -> 0.16456299 | F19: =F18/F6 -> 0.14823951 | G19: =G18/G6 -> 0.14960473 | H19: =H18/H6 -> 0.17325496 | I19: =I18/I6 -> 0.1563052 | J19: =J18/J6 -> 0.16239006 | ... M19: =M18/M6 -> 0.17435982
B21: INTEREST | C21: ='Data Sheet'!B27 -> 3691 | D21: ='Data Sheet'!C27 -> 3849 | E21: ='Data Sheet'!D27 -> 8052 | F21: ='Data Sheet'!E27 -> 16495 | G21: ='Data Sheet'!F27 -> 22027 | H21: ='Data Sheet'!G27 -> 21189 | I21: ='Data Sheet'!H27 -> 14584 | J21: ='Data Sheet'!I27 -> 19571 | ... L21: ='Data Sheet'!K27 -> 24269 | M21: =IFERROR(SUM('Data Sheet'!H46:K46),0) -> 26631
B22: INTEREST % OF SALES | C22: =C21/C6 -> 0.01354083 | D22: =D21/D6 -> 0.0126631 | E22: =E21/E6 -> 0.020602677 | F22: =F21/F6 -> 0.029023273 | G22: =G21/G6 -> 0.036915997 | H22: =H21/H6 -> 0.045440021 | I22: =I21/I6 -> 0.02099405 | J22: =J21/J6 -> 0.022331229 | ... M22: =M21/M6 -> 0.025992926
B24: DEPRECIATION | C24: ='Data Sheet'!B26 -> 11565 | D24: ='Data Sheet'!C26 -> 11646 | E24: ='Data Sheet'!D26 -> 16706 | F24: ='Data Sheet'!E26 -> 20934 | G24: ='Data Sheet'!F26 -> 22203 | H24: ='Data Sheet'!G26 -> 26572 | I24: ='Data Sheet'!H26 -> 29782 | J24: ='Data Sheet'!I26 -> 40303 | ... L24: ='Data Sheet'!K26 -> 53136 | M24: =IFERROR(SUM('Data Sheet'!H45:K45),0) -> 56359
B25: DEPRECIATION % OF SALES | C25: =C24/C6 -> 0.042427444 | D25: =D24/D6 -> 0.038315008 | E25: =E24/E6 -> 0.042745693 | F25: =F24/F6 -> 0.03683378 | G25: =G24/G6 -> 0.037210963 | H25: =H24/H6 -> 0.056983918 | I25: =I24/I6 -> 0.04287197 | J25: =J24/J6 -> 0.045987202 | ... M25: =M24/M6 -> 0.055008648
B27: EARNING BEFORE TAX | C27: =IFERROR(C18-SUM(C21,C24),0) -> 26525 | D27: =IFERROR(D18-SUM(D21,D24),0) -> 30812 | E27: =IFERROR(E18-SUM(E21,E24),0) -> 39557 | F27: =IFERROR(F18-SUM(F21,F24),0) -> 46821 | G27: =IFERROR(G18-SUM(G21,G24),0) -> 45036 | H27: =IFERROR(H18-SUM(H21,H24),0) -> 33029 | I27: =IFERROR(I18-SUM(I21,I24),0) -> 64215 | J27: =IFERROR(J18-SUM(J21,J24),0) -> 82444 | ... M27: =IFERROR(M18-SUM(M21,M24),0) -> 95650
B28: EBT % OF SALES | C28: =C27/C6 -> 0.09730981 | D28: =D27/D6 -> 0.1013706 | E28: =E27/E6 -> 0.10121462 | F28: =F27/F6 -> 0.08238246 | G28: =G27/G6 -> 0.075477769 | H28: =H27/H6 -> 0.070831019 | I28: =I27/I6 -> 0.092439176 | J28: =J27/J6 -> 0.09407163 | ... M28: =M27/M6 -> 0.093358242
B30: TAX | C30: =IFERROR('Data Sheet'!B29,0) -> 8876 | D30: =IFERROR('Data Sheet'!C29,0) -> 10201 | E30: =IFERROR('Data Sheet'!D29,0) -> 13346 | F30: =IFERROR('Data Sheet'!E29,0) -> 15390 | G30: =IFERROR('Data Sheet'!F29,0) -> 13726 | H30: =IFERROR('Data Sheet'!G29,0) -> 1722 | I30: =IFERROR('Data Sheet'!H29,0) -> 15970 | J30: =IFERROR('Data Sheet'!I29,0) -> 20376 | ... L30: =IFERROR('Data Sheet'!K29,0) -> 25230 | M30: =IFERROR(SUM('Data Sheet'!H48:K48),0) -> 27642
B31: EFFECTIVE TAX RATE | C31: =C30/C27 -> 0.33462771 | D31: =D30/D27 -> 0.33107231 | E31: =E30/E27 -> 0.33738656 | F31: =F30/F27 -> 0.32869866 | G31: =G30/G27 -> 0.3047784 | H31: =H30/H27 -> 0.052136002 | I31: =I30/I27 -> 0.24869579 | J31: =J30/J27 -> 0.24714958 | ... M31: =M30/M27 -> 0.28899111
B33: NET PROFIT | C33: =C27-C30 -> 17649 | D33: =D27-D30 -> 20611 | E33: =E27-E30 -> 26211 | F33: =F27-F30 -> 31431 | G33: =G27-G30 -> 31310 | H33: =H27-H30 -> 31307 | I33: =I27-I30 -> 48245 | J33: =J27-J30 -> 62068 | ... M33: =M27-M30 -> 68008
B34: NET MARGINS | C34: =C33/C6 -> 0.064747251 | D34: =D33/D6 -> 0.067809603 | E34: =E33/E6 -> 0.067066166 | F34: =F33/F6 -> 0.055303456 | G34: =G33/G6 -> 0.052473776 | H34: =H33/H6 -> 0.067138173 | I34: =I33/I6 -> 0.069449943 | J34: =J33/J6 -> 0.070821866 | ... M34: =M33/M6 -> 0.06637854
B36: NO. OF EQUITY SHARES | C36: ='Data Sheet'!B93 -> 1382.58 | D36: ='Data Sheet'!C93 -> 1387.22 | E36: ='Data Sheet'!D93 -> 1351.39 | F36: ='Data Sheet'!E93 -> 1352.26 | G36: ='Data Sheet'!F93 -> 1352.37 | H36: ='Data Sheet'!G93 -> 1267.89 | I36: ='Data Sheet'!H93 -> 1352.98 | J36: ='Data Sheet'!I93 -> 1353.12 | ... L36: ='Data Sheet'!K93 -> 1353.24 | M36: -
B39: EARNING PER SHARE | C39: =IFERROR(C33/C36,0) -> 12.765265 | D39: =IFERROR(D33/D36,0) -> 14.857773 | E39: =IFERROR(E33/E36,0) -> 19.395585 | F39: =IFERROR(F33/F36,0) -> 23.243311 | G39: =IFERROR(G33/G36,0) -> 23.151948 | H39: =IFERROR(H33/H36,0) -> 24.692205 | I39: =IFERROR(I33/I36,0) -> 35.658325 | J39: =IFERROR(J33/J36,0) -> 45.870285 | ... L39: =IFERROR(L33/L36,0) -> 46.527593 | M39: -
B40: EPS GROWTH% | D40: =IFERROR(D39/C39-1,0) -> 0.16392203 | E40: =IFERROR(E39/D39-1,0) -> 0.30541671 | F40: =IFERROR(F39/E39-1,0) -> 0.19838153 | G40: =IFERROR(G39/F39-1,0) -> -0.0039307281 | H40: =IFERROR(H39/G39-1,0) -> 0.066528186 | I40: =IFERROR(I39/H39-1,0) -> 0.4441126 | J40: =IFERROR(J39/I39-1,0) -> 0.28638363 | K40: =IFERROR(K39/J39-1,0) -> 0.012439118 | L40: =IFERROR(L39/K39-1,0) -> 0.0018673675
B42: DIVIDEND PER SHARE | C42: =IFERROR('Data Sheet'!B31/C36,0) -> 2.2388578 | D42: =IFERROR('Data Sheet'!C31/D36,0) -> 2.3463474 | E42: =IFERROR('Data Sheet'!D31/E36,0) -> 2.6292928 | F42: =IFERROR('Data Sheet'!E31/F36,0) -> 2.8484907 | G42: =IFERROR('Data Sheet'!F31/G36,0) -> 3.0467624 | H42: =IFERROR('Data Sheet'!G31/H36,0) -> 3.558274 | I42: =IFERROR('Data Sheet'!H31/I36,0) -> 4.0000591 | J42: =IFERROR('Data Sheet'!I31/J36,0) -> 4.5002661 | ... L42: =IFERROR('Data Sheet'!K31/L36,0) -> 5.4998374 | M42: –
B43: DIVIDEND PAYOUT RATIO | C43: =IFERROR(C42/C39,0) -> 0.17538671 | D43: =IFERROR(D42/D39,0) -> 0.15792053 | E43: =IFERROR(E42/E39,0) -> 0.13556141 | F43: =IFERROR(F42/F39,0) -> 0.12255098 | G43: =IFERROR(G42/G39,0) -> 0.13159853 | H43: =IFERROR(H42/H39,0) -> 0.14410515 | I43: =IFERROR(I42/I39,0) -> 0.11217743 | J43: =IFERROR(J42/J39,0) -> 0.098108526 | ... L43: =IFERROR(L42/L39,0) -> 0.11820593
B45: RETAINED EARNINGS | C45: =IFERROR(1-C43,0) -> 0.82461329 | D45: =IFERROR(1-D43,0) -> 0.84207947 | E45: =IFERROR(1-E43,0) -> 0.86443859 | F45: =IFERROR(1-F43,0) -> 0.87744902 | G45: =IFERROR(1-G43,0) -> 0.86840147 | H45: =IFERROR(1-H43,0) -> 0.85589485 | I45: =IFERROR(1-I43,0) -> 0.88782257 | J45: =IFERROR(1-J43,0) -> 0.90189147 | ... L45: =IFERROR(1-L43,0) -> 0.88179407 | M45: -
A48: # | B48: BALANCESHEET
B49: ='Data Sheet'!A57 -> Equity Share Capital | C49: ='Data Sheet'!B57 -> 2948 | D49: ='Data Sheet'!C57 -> 2959 | E49: ='Data Sheet'!D57 -> 5922 | F49: ='Data Sheet'!E57 -> 5926 | G49: ='Data Sheet'!F57 -> 6339 | H49: ='Data Sheet'!G57 -> 6445 | I49: ='Data Sheet'!H57 -> 6765 | ... L49: ='Data Sheet'!K57 -> 13532
B50: ='Data Sheet'!A58 -> Reserves | C50: ='Data Sheet'!B58 -> 228608 | D50: ='Data Sheet'!C58 -> 260750 | E50: ='Data Sheet'!D58 -> 287584 | F50: ='Data Sheet'!E58 -> 381186 | G50: ='Data Sheet'!F58 -> 442827 | H50: ='Data Sheet'!G58 -> 693727 | I50: ='Data Sheet'!H58 -> 772720 | ... L50: ='Data Sheet'!K58 -> 829668
B51: ='Data Sheet'!A59 -> Borrowings | C51: ='Data Sheet'!B59 -> 194714 | D51: ='Data Sheet'!C59 -> 217475 | E51: ='Data Sheet'!D59 -> 239843 | F51: ='Data Sheet'!E59 -> 307714 | G51: ='Data Sheet'!F59 -> 355133 | H51: ='Data Sheet'!G59 -> 278962 | I51: ='Data Sheet'!H59 -> 319158 | ... L51: ='Data Sheet'!K59 -> 374313
B52: ='Data Sheet'!A60 -> Other Liabilities | C52: ='Data Sheet'!B60 -> 172727 | D52: ='Data Sheet'!C60 -> 225618 | E52: ='Data Sheet'!D60 -> 277924 | F52: ='Data Sheet'!E60 -> 302804 | G52: ='Data Sheet'!F60 -> 358716 | H52: ='Data Sheet'!G60 -> 340931 | I52: ='Data Sheet'!H60 -> 399979 | ... L52: ='Data Sheet'!K60 -> 732200
B53: TOTAL LIABILTIES | C53: ='Data Sheet'!B61 -> 598997 | D53: ='Data Sheet'!C61 -> 706802 | E53: ='Data Sheet'!D61 -> 811273 | F53: ='Data Sheet'!E61 -> 997630 | G53: ='Data Sheet'!F61 -> 1163015 | H53: ='Data Sheet'!G61 -> 1320065 | I53: ='Data Sheet'!H61 -> 1498622 | J53: ='Data Sheet'!I61 -> 1605882 | ... L53: ='Data Sheet'!K61 -> 1949713
B55: FIXED ASSEST NET BLOCK | C55: ='Data Sheet'!B62 -> 184910 | D55: ='Data Sheet'!C62 -> 198526 | E55: ='Data Sheet'!D62 -> 403885 | F55: ='Data Sheet'!E62 -> 398374 | G55: ='Data Sheet'!F62 -> 532658 | H55: ='Data Sheet'!G62 -> 541258 | I55: ='Data Sheet'!H62 -> 627798 | J55: ='Data Sheet'!I62 -> 724805 | ... L55: ='Data Sheet'!K62 -> 999393
B56: CAPITAL WORK IN PROGRESS | C56: ='Data Sheet'!B63 -> 228697 | D56: ='Data Sheet'!C63 -> 324837 | E56: ='Data Sheet'!D63 -> 187022 | F56: ='Data Sheet'!E63 -> 179463 | G56: ='Data Sheet'!F63 -> 109106 | H56: ='Data Sheet'!G63 -> 125953 | I56: ='Data Sheet'!H63 -> 172506 | J56: ='Data Sheet'!I63 -> 293752 | ... L56: ='Data Sheet'!K63 -> 262358
B57: INVESTMENTS | C57: ='Data Sheet'!B64 -> 84015 | D57: ='Data Sheet'!C64 -> 82899 | E57: ='Data Sheet'!D64 -> 82862 | F57: ='Data Sheet'!E64 -> 235635 | G57: ='Data Sheet'!F64 -> 276767 | H57: ='Data Sheet'!G64 -> 364828 | I57: ='Data Sheet'!H64 -> 394264 | J57: ='Data Sheet'!I64 -> 235560 | ... L57: ='Data Sheet'!K64 -> 242381
B58: OTHER ASSESTS | C58: =IFERROR('Data Sheet'!B65-SUM('Data Sheet'!B67:B69),0) -> 39396 | D58: =IFERROR('Data Sheet'!C65-SUM('Data Sheet'!C67:C69),0) -> 40389 | E58: =IFERROR('Data Sheet'!D65-SUM('Data Sheet'!D67:D69),0) -> 54857 | F58: =IFERROR('Data Sheet'!E65-SUM('Data Sheet'!E67:E69),0) -> 75427 | G58: =IFERROR('Data Sheet'!F65-SUM('Data Sheet'!F67:F69),0) -> 120005 | H58: =IFERROR('Data Sheet'!G65-SUM('Data Sheet'!G67:G69),0) -> 169943 | I58: =IFERROR('Data Sheet'!H65-SUM('Data Sheet'!H67:H69),0) -> 136458 | J58: =IFERROR('Data Sheet'!I65-SUM('Data Sheet'!I67:I69),0) -> 114645 | ... L58: =IFERROR('Data Sheet'!K65-SUM('Data Sheet'!K67:K69),0) -> 150896
B59: TOTAL NON CURRENT ASSESTS | C59: =IFERROR(SUM(C55:C58),0) -> 537018 | D59: =IFERROR(SUM(D55:D58),0) -> 646651 | E59: =IFERROR(SUM(E55:E58),0) -> 728626 | F59: =IFERROR(SUM(F55:F58),0) -> 888899 | G59: =IFERROR(SUM(G55:G58),0) -> 1038536 | H59: =IFERROR(SUM(H55:H58),0) -> 1201982 | I59: =IFERROR(SUM(I55:I58),0) -> 1331026 | J59: =IFERROR(SUM(J55:J58),0) -> 1368762 | ... L59: =IFERROR(SUM(L55:L58),0) -> 1655028
B61: RECEIVABLES | C61: ='Data Sheet'!B67 -> 4465 | D61: ='Data Sheet'!C67 -> 8177 | E61: ='Data Sheet'!D67 -> 17555 | F61: ='Data Sheet'!E67 -> 30089 | G61: ='Data Sheet'!F67 -> 19656 | H61: ='Data Sheet'!G67 -> 19014 | I61: ='Data Sheet'!H67 -> 23640 | J61: ='Data Sheet'!I67 -> 28448 | ... L61: ='Data Sheet'!K67 -> 42121
B62: INVENTORY | C62: ='Data Sheet'!B68 -> 46486 | D62: ='Data Sheet'!C68 -> 48951 | E62: ='Data Sheet'!D68 -> 60837 | F62: ='Data Sheet'!E68 -> 67561 | G62: ='Data Sheet'!F68 -> 73903 | H62: ='Data Sheet'!G68 -> 81672 | I62: ='Data Sheet'!H68 -> 107778 | J62: ='Data Sheet'!I68 -> 140008 | ... L62: ='Data Sheet'!K68 -> 146062
B63: CASH AND BANK | C63: ='Data Sheet'!B69 -> 11028 | D63: ='Data Sheet'!C69 -> 3023 | E63: ='Data Sheet'!D69 -> 4255 | F63: ='Data Sheet'!E69 -> 11081 | G63: ='Data Sheet'!F69 -> 30920 | H63: ='Data Sheet'!G69 -> 17397 | I63: ='Data Sheet'!H69 -> 36178 | J63: ='Data Sheet'!I69 -> 68664 | ... L63: ='Data Sheet'!K69 -> 106502
B64: TOTAL CURRENT ASSETS | C64: =IFERROR(SUM(C61:C63),0) -> 61979 | D64: =IFERROR(SUM(D61:D63),0) -> 60151 | E64: =IFERROR(SUM(E61:E63),0) -> 82647 | F64: =IFERROR(SUM(F61:F63),0) -> 108731 | G64: =IFERROR(SUM(G61:G63),0) -> 124479 | H64: =IFERROR(SUM(H61:H63),0) -> 118083 | I64: =IFERROR(SUM(I61:I63),0) -> 167596 | J64: =IFERROR(SUM(J61:J63),0) -> 237120 | ... L64: =IFERROR(SUM(L61:L63),0) -> 294685
B66: TOTAL ASSETS | C66: =C64+C59 -> 598997 | D66: =D64+D59 -> 706802 | E66: =E64+E59 -> 811273 | F66: =F64+F59 -> 997630 | G66: =G64+G59 -> 1163015 | H66: =H64+H59 -> 1320065 | I66: =I64+I59 -> 1498622 | J66: =J64+J59 -> 1605882 | ... L66: =L64+L59 -> 1949713
B68: CHECK | C68: =C66=C53 -> TRUE | D68: =D66=D53 -> TRUE | E68: =E66=E53 -> TRUE | F68: =F66=F53 -> TRUE | G68: =G66=G53 -> TRUE | H68: =H66=H53 -> TRUE | I68: =I66=I53 -> TRUE | J68: =J66=J53 -> TRUE | ... L68: =L66=L53 -> TRUE
A70: # | B70: CASH FLOW STATEMENT
B71: Operating activities
B72: {=CFS!B4:B9} -> Profit from operations | C72: =CFS!D4 -> 38887 | D72: =CFS!E4 -> 44170 | E72: =CFS!F4 -> 62765 | F72: =CFS!G4 -> 83319 | G72: =CFS!H4 -> 85347 | H72: =CFS!I4 -> 80129 | I72: =CFS!J4 -> 113726 | J72: =CFS!K4 -> 140963 | ... L72: =CFS!M4 -> 166904
B73: Receivables | C73: =CFS!D5 -> -6880 | D73: =CFS!E5 -> -8511 | E73: =CFS!F5 -> -21991 | F73: =CFS!G5 -> -40136 | G73: =CFS!H5 -> -13792 | H73: =CFS!I5 -> 959 | I73: =CFS!J5 -> -14180 | J73: =CFS!K5 -> 13194 | ... L73: =CFS!M5 -> -17837
B74: Inventory | C74: =CFS!D6 -> 6758 | D74: =CFS!E6 -> -6899 | E74: =CFS!F6 -> -10474 | F74: =CFS!G6 -> -6724 | G74: =CFS!H6 -> -6342 | H74: =CFS!I6 -> -7769 | I74: =CFS!J6 -> -24983 | J74: =CFS!K6 -> -32228 | ... L74: =CFS!M6 -> 3134
B75: Payables | C75: =CFS!D7 -> 7951 | D75: =CFS!E7 -> 30873 | E75: =CFS!F7 -> 51003 | F75: =CFS!G7 -> 18078 | G75: =CFS!H7 -> 38050 | H75: =CFS!I7 -> -43148 | I75: =CFS!J7 -> 39888 | J75: =CFS!K7 -> -600 | ... L75: =CFS!M7 -> 38427
B76: Working capital changes | C76: =CFS!D8 -> 7829 | D76: =CFS!E8 -> 15463 | E76: =CFS!F8 -> 18538 | F76: =CFS!G8 -> -28782 | G76: =CFS!H8 -> 17916 | H76: =CFS!I8 -> -49958 | I76: =CFS!J8 -> 725 | J76: =CFS!K8 -> -19634 | ... L76: =CFS!M8 -> 23724
B77: Direct taxes | C77: =CFS!D9 -> -8582 | D77: =CFS!E9 -> -10083 | E77: =CFS!F9 -> -9844 | F77: =CFS!G9 -> -12191 | G77: =CFS!H9 -> -8386 | H77: =CFS!I9 -> -3213 | I77: =CFS!J9 -> -3797 | J77: =CFS!K9 -> -6297 | ... L77: =CFS!M9 -> -11925
B78: Cash from Operating Activities | C78: =IFERROR(SUM(C72:C77),0) -> 45963 | D78: =IFERROR(SUM(D72:D77),0) -> 65013 | E78: =IFERROR(SUM(E72:E77),0) -> 89997 | F78: =IFERROR(SUM(F72:F77),0) -> 13564 | G78: =IFERROR(SUM(G72:G77),0) -> 112793 | H78: =IFERROR(SUM(H72:H77),0) -> -23000 | I78: =IFERROR(SUM(I72:I77),0) -> 111379 | J78: =IFERROR(SUM(J72:J77),0) -> 95398 | ... L78: =IFERROR(SUM(L72:L77),0) -> 202427
B80: INVESTING ACTIVITIES
B81: {=CFS!B11:B17} -> Fixed assets purchased | C81: =IFERROR(CFS!D11,0) -> -46898 | D81: =IFERROR(CFS!E11,0) -> -78109 | E81: =IFERROR(CFS!F11,0) -> -73953 | F81: =IFERROR(CFS!G11,0) -> -93626 | G81: =IFERROR(CFS!H11,0) -> -76517 | H81: =IFERROR(CFS!I11,0) -> -105837 | I81: =IFERROR(CFS!J11,0) -> -100145 | J81: =IFERROR(CFS!K11,0) -> -140988 | ... L81: =IFERROR(CFS!M11,0) -> -139967
B82: Fixed assets sold | C82: =IFERROR(CFS!D12,0) -> 344 | D82: =IFERROR(CFS!E12,0) -> 1482 | E82: =IFERROR(CFS!F12,0) -> 999 | F82: =IFERROR(CFS!G12,0) -> 849 | G82: =IFERROR(CFS!H12,0) -> 964 | H82: =IFERROR(CFS!I12,0) -> 2319 | I82: =IFERROR(CFS!J12,0) -> 3137 | J82: =IFERROR(CFS!K12,0) -> 9186 | ... L82: =IFERROR(CFS!M12,0) -> 2343
B83: Investments purchased | C83: =IFERROR(CFS!D13,0) -> -715334 | D83: =IFERROR(CFS!E13,0) -> -654760 | E83: =IFERROR(CFS!F13,0) -> -533984 | F83: =IFERROR(CFS!G13,0) -> -1107439 | G83: =IFERROR(CFS!H13,0) -> -1156843 | H83: =IFERROR(CFS!I13,0) -> -689866 | I83: =IFERROR(CFS!J13,0) -> -667878 | J83: =IFERROR(CFS!K13,0) -> -471822 | ... L83: =IFERROR(CFS!M13,0) -> -684340
B84: Investments sold | C84: =IFERROR(CFS!D14,0) -> 721182 | D84: =IFERROR(CFS!E14,0) -> 663990 | E84: =IFERROR(CFS!F14,0) -> 537504 | F84: =IFERROR(CFS!G14,0) -> 1103615 | G84: =IFERROR(CFS!H14,0) -> 1174796 | H84: =IFERROR(CFS!I14,0) -> 642551 | I84: =IFERROR(CFS!J14,0) -> 668137 | J84: =IFERROR(CFS!K14,0) -> 501266 | ... L84: =IFERROR(CFS!M14,0) -> 672558
B85: Interest received | C85: =IFERROR(CFS!D15,0) -> 2942 | D85: =IFERROR(CFS!E15,0) -> 1110 | E85: =IFERROR(CFS!F15,0) -> 1310 | F85: =IFERROR(CFS!G15,0) -> 972 | G85: =IFERROR(CFS!H15,0) -> 1441 | H85: =IFERROR(CFS!I15,0) -> 8400 | I85: =IFERROR(CFS!J15,0) -> 5933 | J85: =IFERROR(CFS!K15,0) -> 11103 | ... L85: =IFERROR(CFS!M15,0) -> 15833
B86: Dividends received | C86: =IFERROR(CFS!D16,0) -> 732 | D86: =IFERROR(CFS!E16,0) -> 345 | E86: =IFERROR(CFS!F16,0) -> 1021 | F86: =IFERROR(CFS!G16,0) -> 501 | G86: =IFERROR(CFS!H16,0) -> 78 | H86: =IFERROR(CFS!I16,0) -> 26 | I86: =IFERROR(CFS!J16,0) -> 19 | J86: =IFERROR(CFS!K16,0) -> 20 | ... L86: =IFERROR(CFS!M16,0) -> 612
B87: Other investing items | C87: =IFERROR(CFS!D17,0) -> 846 | D87: =IFERROR(CFS!E17,0) -> -259 | E87: =IFERROR(CFS!F17,0) -> -1089 | F87: =IFERROR(CFS!G17,0) -> 621 | G87: =IFERROR(CFS!H17,0) -> -16416 | H87: =IFERROR(CFS!I17,0) -> 22 | I87: =IFERROR(CFS!J17,0) -> -18365 | J87: =IFERROR(CFS!K17,0) -> -1766 | ... L87: =IFERROR(CFS!M17,0) -> -4574
B88: CASH FROM INVESTING ACTIVITIES | C88: =IFERROR(SUM(C81:C87),0) -> -36186 | D88: =IFERROR(SUM(D81:D87),0) -> -66201 | E88: =IFERROR(SUM(E81:E87),0) -> -68192 | F88: =IFERROR(SUM(F81:F87),0) -> -94507 | G88: =IFERROR(SUM(G81:G87),0) -> -72497 | H88: =IFERROR(SUM(H81:H87),0) -> -142385 | I88: =IFERROR(SUM(I81:I87),0) -> -109162 | J88: =IFERROR(SUM(J81:J87),0) -> -93001 | ... L88: =IFERROR(SUM(L81:L87),0) -> -137535
B90: FINANCING ACTIVITIES
B91: {=CFS!B19:B26} -> Proceeds from shares | C91: =CFS!D19 -> 288 | D91: =CFS!E19 -> 811 | E91: =CFS!F19 -> 406 | F91: =CFS!G19 -> 230 | G91: =CFS!H19 -> 129 | H91: =CFS!I19 -> 5 | I91: =CFS!J19 -> 455 | J91: =CFS!K19 -> 479 | ... L91: =CFS!M19 -> 0
B92: Proceeds from borrowings | C92: =CFS!D20 -> 34673 | D92: =CFS!E20 -> 31728 | E92: =CFS!F20 -> 36970 | F92: =CFS!G20 -> 106701 | G92: =CFS!H20 -> 53760 | H92: =CFS!I20 -> 46421 | I92: =CFS!J20 -> 59343 | J92: =CFS!K20 -> 67134 | ... L92: =CFS!M20 -> 51002
B93: Repayment of borrowings | C93: =CFS!D21 -> -21693 | D93: =CFS!E21 -> -18542 | E93: =CFS!F21 -> -19813 | F93: =CFS!G21 -> -20245 | G93: =CFS!H21 -> -18179 | H93: =CFS!I21 -> -116921 | I93: =CFS!J21 -> -49493 | J93: =CFS!K21 -> -29059 | ... L93: =CFS!M21 -> -31755
B94: Interest paid fin | C94: =CFS!D22 -> -9224 | D94: =CFS!E22 -> -12920 | E94: =CFS!F22 -> -17669 | F94: =CFS!G22 -> -23338 | G94: =CFS!H22 -> -28508 | H94: =CFS!I22 -> -18340 | I94: =CFS!J22 -> -26349 | J94: =CFS!K22 -> -21650 | ... L94: =CFS!M22 -> -41024
B95: Dividends paid | C95: =CFS!D23 -> -7259 | D95: =CFS!E23 -> -53 | E95: =CFS!F23 -> -3916 | F95: =CFS!G23 -> -4282 | G95: =CFS!H23 -> -4592 | H95: =CFS!I23 -> -3921 | I95: =CFS!J23 -> -4297 | J95: =CFS!K23 -> -5083 | ... L95: =CFS!M23 -> -7180
B96: Financial liabilities | C96: =CFS!D24 -> 0 | D96: =CFS!E24 -> 0 | E96: =CFS!F24 -> 0 | F96: =CFS!G24 -> 0 | G96: =CFS!H24 -> -1062 | H96: =CFS!I24 -> -1022 | I96: =CFS!J24 -> -2132 | J96: =CFS!K24 -> -1406 | ... L96: =CFS!M24 -> -2956
B97: Share application money | C97: =CFS!D25 -> 8 | D97: =CFS!E25 -> 4 | E97: =CFS!F25 -> 15 | F97: =CFS!G25 -> 2 | G97: =CFS!H25 -> 1 | H97: =CFS!I25 -> 0 | I97: =CFS!J25 -> 0 | J97: =CFS!K25 -> 0 | ... L97: =CFS!M25 -> 0
B98: Other financing items | C98: =CFS!D26 -> -3 | D98: =CFS!E26 -> 7589 | E98: =CFS!F26 -> 2006 | F98: =CFS!G26 -> -3162 | G98: =CFS!H26 -> -4090 | H98: =CFS!I26 -> 195682 | I98: =CFS!J26 -> 39762 | J98: =CFS!K26 -> 40 | ... L98: =CFS!M26 -> 22
B99: CASH FROM FINANCING ACTIVITIES | C99: =IFERROR(SUM(C91:C98),0) -> -3210 | D99: =IFERROR(SUM(D91:D98),0) -> 8617 | E99: =IFERROR(SUM(E91:E98),0) -> -2001 | F99: =IFERROR(SUM(F91:F98),0) -> 55906 | G99: =IFERROR(SUM(G91:G98),0) -> -2541 | H99: =IFERROR(SUM(H91:H98),0) -> 101904 | I99: =IFERROR(SUM(I91:I98),0) -> 17289 | J99: =IFERROR(SUM(J91:J98),0) -> 10455 | ... L99: =IFERROR(SUM(L91:L98),0) -> -31891
B101: NET CASH FLOW | C101: =IFERROR(SUM(C99+C88+C78),0) -> 6567 | D101: =IFERROR(SUM(D99+D88+D78),0) -> 7429 | E101: =IFERROR(SUM(E99+E88+E78),0) -> 19804 | F101: =IFERROR(SUM(F99+F88+F78),0) -> -25037 | G101: =IFERROR(SUM(G99+G88+G78),0) -> 37755 | H101: =IFERROR(SUM(H99+H88+H78),0) -> -63481 | I101: =IFERROR(SUM(I99+I88+I78),0) -> 19506 | J101: =IFERROR(SUM(J99+J88+J78),0) -> 12852 | ... L101: =IFERROR(SUM(L99+L88+L78),0) -> 33001

Sheet FORECASTING
B2: ='Data Sheet'!$B$1& "-" &'Data Sheet'!A17&" Forecasting" -> RELIANCE INDUSTRIES LTD-Sales Forecasting | H2: ='Data Sheet'!$B$1& "-" & 'HISTORICAL FC'!B18 & " Forecasting" -> RELIANCE INDUSTRIES LTD-EBITDA Forecasting | M2: ='Data Sheet'!$B$1& "-" & 'HISTORICAL FC'!B39& " Forecasting" -> RELIANCE INDUSTRIES LTD-EARNING PER SHARE Forecasting
B3: Year Weight | C3: Year | D3: Sales | E3: Sales Growth | H3: Year Weight | I3: Year | J3: Sales | K3: Sales Growth | M3: Year Weight | N3: Year | O3: Sales | P3: Sales Growth
B4: 1 | C4: 2016 | D4: {=TRANSPOSE('Data Sheet'!B17:K17)} -> 272583 | H4: 1 | I4: 2016 | J4: {=TRANSPOSE( 'HISTORICAL FC'!C18:L18)} -> 41781 | M4: 1 | N4: 2016 | O4: {=TRANSPOSE('HISTORICAL FC'!C39:L39)} -> 12.765265
B5: 2 | C5: 2017 | D5: 303954 | E5: =D5/D4-1 -> 0.11508788 | H5: 2 | I5: 2017 | J5: 46307 | K5: =J5/J4-1 -> 0.10832675 | M5: 2 | N5: 2017 | O5: 14.857773 | P5: =O5/O4-1 -> 0.16392203
B6: 3 | C6: 2018 | D6: 390823 | E6: =D6/D5-1 -> 0.28579654 | H6: 3 | I6: 2018 | J6: 64315 | K6: =J6/J5-1 -> 0.38888289 | M6: 3 | N6: 2018 | O6: 19.395585 | P6: =O6/O5-1 -> 0.30541671
B7: 4 | C7: 2019 | D7: 568337 | E7: =D7/D6-1 -> 0.45420561 | H7: 4 | I7: 2019 | J7: 84250 | K7: =J7/J6-1 -> 0.3099588 | M7: 4 | N7: 2019 | O7: 23.243311 | P7: =O7/O6-1 -> 0.19838153
B8: 5 | C8: 2020 | D8: 596679 | E8: =D8/D7-1 -> 0.0498683 | H8: 5 | I8: 2020 | J8: 89266 | K8: =J8/J7-1 -> 0.059537092 | M8: 5 | N8: 2020 | O8: 23.151948 | P8: =O8/O7-1 -> -0.0039307281
B9: 6 | C9: 2021 | D9: 466307 | E9: =D9/D8-1 -> -0.21849604 | H9: 6 | I9: 2021 | J9: 80790 | K9: =J9/J8-1 -> -0.094952165 | M9: 6 | N9: 2021 | O9: 24.692205 | P9: =O9/O8-1 -> 0.066528186
B10: 7 | C10: 2022 | D10: 694673 | E10: =D10/D9-1 -> 0.48973316 | H10: 7 | I10: 2022 | J10: 108581 | K10: =J10/J9-1 -> 0.34399059 | M10: 7 | N10: 2022 | O10: 35.658325 | P10: =O10/O9-1 -> 0.4441126
B11: 8 | C11: 2023 | D11: 876396 | E11: =D11/D10-1 -> 0.26159502 | H11: 8 | I11: 2023 | J11: 142318 | K11: =J11/J10-1 -> 0.31070813 | M11: 8 | N11: 2023 | O11: 45.870285 | P11: =O11/O10-1 -> 0.28638363
B12: 9 | C12: 2024 | D12: 899041 | E12: =D12/D11-1 -> 0.025838776 | H12: 9 | I12: 2024 | J12: 162498 | K12: =J12/J11-1 -> 0.14179513 | M12: 9 | N12: 2024 | O12: 46.440871 | P12: =O12/O11-1 -> 0.012439118
B13: 10 | C13: 2025 | D13: 962820 | E13: =D13/D12-1 -> 0.070941147 | H13: 10 | I13: 2025 | J13: 165598 | K13: =J13/J12-1 -> 0.019077158 | M13: 10 | N13: 2025 | O13: 46.527593 | P13: =O13/O12-1 -> 0.0018673675
B14: 11 | C14: 2026 | D14: =FORECAST(B14,_xlfn.ANCHORARRAY($D$4),$B$4:$B$13) -> 1038302.7 | E14: =D14/D13-1 -> 0.078397554 | H14: 11 | I14: 2026 | J14: =FORECAST(H14,_xlfn.ANCHORARRAY($J$4),$H$4:$H$13) -> 177977.8 | K14: =J14/J13-1 -> 0.074758149 | M14: 11 | N14: 2026 | O14: =FORECAST(M14,_xlfn.ANCHORARRAY($O$4),$M$4:$M$13) -> 52.463697 | P14: =O14/O13-1 -> 0.12758245
B15: 12 | C15: 2027 | D15: =FORECAST(B15,_xlfn.ANCHORARRAY($D$4),$B$4:$B$13) -> 1117419.4 | E15: =D15/D14-1 -> 0.076198031 | H15: 12 | I15: 2027 | J15: =FORECAST(H15,_xlfn.ANCHORARRAY($J$4),$H$4:$H$13) -> 192415.51 | K15: =J15/J14-1 -> 0.081120843 | M15: 12 | N15: 2027 | O15: =FORECAST(M15,_xlfn.ANCHORARRAY($O$4),$M$4:$M$13) -> 56.682494 | P15: =O15/O14-1 -> 0.080413634
B16: 13 | C16: 2028 | D16: =FORECAST(B16,_xlfn.ANCHORARRAY($D$4),$B$4:$B$13) -> 1196536 | E16: =D16/D15-1 -> 0.070802983 | H16: 13 | I16: 2028 | J16: =FORECAST(H16,_xlfn.ANCHORARRAY($J$4),$H$4:$H$13) -> 206853.22 | K16: =J16/J15-1 -> 0.07503402 | M16: 13 | N16: 2028 | O16: =FORECAST(M16,_xlfn.ANCHORARRAY($O$4),$M$4:$M$13) -> 60.90129 | P16: =O16/O15-1 -> 0.074428563
B17: 14 | C17: 2029 | D17: =FORECAST(B17,_xlfn.ANCHORARRAY($D$4),$B$4:$B$13) -> 1275652.6 | E17: =D17/D16-1 -> 0.066121392 | H17: 14 | I17: 2029 | J17: =FORECAST(H17,_xlfn.ANCHORARRAY($J$4),$H$4:$H$13) -> 221290.93 | K17: =J17/J16-1 -> 0.069796879 | M17: 14 | N17: 2029 | O17: =FORECAST(M17,_xlfn.ANCHORARRAY($O$4),$M$4:$M$13) -> 65.120087 | P17: =O17/O16-1 -> 0.069272696

Sheet RATIO ANALYSIS
B2: =" Ratio Analysis Of -"&'Data Sheet'!B1 -> Ratio Analysis Of -RELIANCE INDUSTRIES LTD
B3: YEARS | C3: ='Data Sheet'!B56 -> 42460 | D3: ='Data Sheet'!C56 -> 42825 | E3: ='Data Sheet'!D56 -> 43190 | F3: ='Data Sheet'!E56 -> 43555 | G3: ='Data Sheet'!F56 -> 43921 | H3: ='Data Sheet'!G56 -> 44286 | I3: ='Data Sheet'!H56 -> 44651 | J3: ='Data Sheet'!I56 -> 45016 | ... L3: ='Data Sheet'!K56 -> 45747 | M3: TREND | N3: Mean | O3: Median
B5: Sales Growth | C5: ='HISTORICAL FC'!C7 | D5: =IFERROR('HISTORICAL FC'!D7,0) -> 0.11508788 | E5: =IFERROR('HISTORICAL FC'!E7,0) -> 0.28579654 | F5: =IFERROR('HISTORICAL FC'!F7,0) -> 0.45420561 | G5: =IFERROR('HISTORICAL FC'!G7,0) -> 0.0498683 | H5: =IFERROR('HISTORICAL FC'!H7,0) -> -0.21849604 | I5: =IFERROR('HISTORICAL FC'!I7,0) -> 0.48973316 | J5: =IFERROR('HISTORICAL FC'!J7,0) -> 0.26159502 | K5: =IFERROR('HISTORICAL FC'!K7,0) -> 0.025838776 | L5: =IFERROR('HISTORICAL FC'!L7,0) -> 0.070941147 | N5: =IFERROR(AVERAGE(D5:L5),0) -> 0.17050782 | O5: =IFERROR(MEDIAN(C5:L5),0) -> 0.11508788
B6: EBITDA Margin | D6: =IFERROR('HISTORICAL FC'!D18/'HISTORICAL FC'!C18-1,0) -> 0.10832675 | E6: =IFERROR('HISTORICAL FC'!E18/'HISTORICAL FC'!D18-1,0) -> 0.38888289 | F6: =IFERROR('HISTORICAL FC'!F18/'HISTORICAL FC'!E18-1,0) -> 0.3099588 | G6: =IFERROR('HISTORICAL FC'!G18/'HISTORICAL FC'!F18-1,0) -> 0.059537092 | H6: =IFERROR('HISTORICAL FC'!H18/'HISTORICAL FC'!G18-1,0) -> -0.094952165 | I6: =IFERROR('HISTORICAL FC'!I18/'HISTORICAL FC'!H18-1,0) -> 0.34399059 | J6: =IFERROR('HISTORICAL FC'!J18/'HISTORICAL FC'!I18-1,0) -> 0.31070813 | K6: =IFERROR('HISTORICAL FC'!K18/'HISTORICAL FC'!J18-1,0) -> 0.14179513 | L6: =IFERROR('HISTORICAL FC'!L18/'HISTORICAL FC'!K18-1,0) -> 0.019077158 | N6: =IFERROR(AVERAGE(D6:L6),0) -> 0.17636938 | O6: =IFERROR(MEDIAN(C6:L6),0) -> 0.14179513
B7: EBT Growth | D7: =IFERROR('HISTORICAL FC'!D27/'HISTORICAL FC'!C27-1,0) -> 0.16162111 | E7: =IFERROR('HISTORICAL FC'!E27/'HISTORICAL FC'!D27-1,0) -> 0.28381799 | F7: =IFERROR('HISTORICAL FC'!F27/'HISTORICAL FC'!E27-1,0) -> 0.18363374 | G7: =IFERROR('HISTORICAL FC'!G27/'HISTORICAL FC'!F27-1,0) -> -0.038123919 | H7: =IFERROR('HISTORICAL FC'!H27/'HISTORICAL FC'!G27-1,0) -> -0.26660894 | I7: =IFERROR('HISTORICAL FC'!I27/'HISTORICAL FC'!H27-1,0) -> 0.94420055 | J7: =IFERROR('HISTORICAL FC'!J27/'HISTORICAL FC'!I27-1,0) -> 0.28387448 | K7: =IFERROR('HISTORICAL FC'!K27/'HISTORICAL FC'!J27-1,0) -> 0.074038135 | L7: =IFERROR('HISTORICAL FC'!L27/'HISTORICAL FC'!K27-1,0) -> -0.004009125 | N7: =IFERROR(AVERAGE(D7:L7),0) -> 0.18027156 | O7: =IFERROR(MEDIAN(C7:L7),0) -> 0.16162111
B8: NET Profit Growth | D8: =IFERROR('HISTORICAL FC'!D33/'HISTORICAL FC'!C33-1,0) -> 0.16782821 | E8: =IFERROR('HISTORICAL FC'!E33/'HISTORICAL FC'!D33-1,0) -> 0.27169958 | F8: =IFERROR('HISTORICAL FC'!F33/'HISTORICAL FC'!E33-1,0) -> 0.19915303 | G8: =IFERROR('HISTORICAL FC'!G33/'HISTORICAL FC'!F33-1,0) -> -0.0038497025 | H8: =IFERROR('HISTORICAL FC'!H33/'HISTORICAL FC'!G33-1,0) -> -9.5816033e-05 | I8: =IFERROR('HISTORICAL FC'!I33/'HISTORICAL FC'!H33-1,0) -> 0.54102916 | J8: =IFERROR('HISTORICAL FC'!J33/'HISTORICAL FC'!I33-1,0) -> 0.28651674 | K8: =IFERROR('HISTORICAL FC'!K33/'HISTORICAL FC'!J33-1,0) -> 0.012454083 | L8: =IFERROR('HISTORICAL FC'!L33/'HISTORICAL FC'!K33-1,0) -> 0.0019414077 | N8: =IFERROR(AVERAGE(D8:L8),0) -> 0.16407519 | O8: =IFERROR(MEDIAN(C8:L8),0) -> 0.16782821
B9: Dividend Growth | D9: =IFERROR('HISTORICAL FC'!D42/'HISTORICAL FC'!C42-1,0) -> 0.048010903 | E9: =IFERROR('HISTORICAL FC'!E42/'HISTORICAL FC'!D42-1,0) -> 0.12058975 | F9: =IFERROR('HISTORICAL FC'!F42/'HISTORICAL FC'!E42-1,0) -> 0.083367616 | G9: =IFERROR('HISTORICAL FC'!G42/'HISTORICAL FC'!F42-1,0) -> 0.069605871 | H9: =IFERROR('HISTORICAL FC'!H42/'HISTORICAL FC'!G42-1,0) -> 0.16788695 | I9: =IFERROR('HISTORICAL FC'!I42/'HISTORICAL FC'!H42-1,0) -> 0.12415715 | J9: =IFERROR('HISTORICAL FC'!J42/'HISTORICAL FC'!I42-1,0) -> 0.12504988 | K9: =IFERROR('HISTORICAL FC'!K42/'HISTORICAL FC'!J42-1,0) -> 0.11109469 | L9: =IFERROR('HISTORICAL FC'!L34/'HISTORICAL FC'!K34-1,0) -> -0.064429068 | N9: =IFERROR(AVERAGE(D9:L9),0) -> 0.087259304 | O9: =IFERROR(MEDIAN(C9:L9),0) -> 0.11109469
B11: Gross Margin | C11: =IFERROR('HISTORICAL FC'!C13,0) -> 0.21039096 | D11: =IFERROR('HISTORICAL FC'!D13,0) -> 0.20432697 | E11: =IFERROR('HISTORICAL FC'!E13,0) -> 0.22919327 | F11: =IFERROR('HISTORICAL FC'!F13,0) -> 0.2324941 | G11: =IFERROR('HISTORICAL FC'!G13,0) -> 0.25278584 | H11: =IFERROR('HISTORICAL FC'!H13,0) -> 0.29570219 | I11: =IFERROR('HISTORICAL FC'!I13,0) -> 0.24881779 | J11: =IFERROR('HISTORICAL FC'!J13,0) -> 0.24911227 | ... L11: =IFERROR('HISTORICAL FC'!L13,0) -> 0.27252342 | N11: =IFERROR(AVERAGE(C11:L11),0) -> 0.24707581 | O11: =IFERROR(MEDIAN(C11:L11),0) -> 0.24896503
B12: EBITDA Margin | C12: =IFERROR('HISTORICAL FC'!C19,0) -> 0.15327808 | D12: =IFERROR('HISTORICAL FC'!D19,0) -> 0.15234871 | E12: =IFERROR('HISTORICAL FC'!E19,0) -> 0.16456299 | F12: =IFERROR('HISTORICAL FC'!F19,0) -> 0.14823951 | G12: =IFERROR('HISTORICAL FC'!G19,0) -> 0.14960473 | H12: =IFERROR('HISTORICAL FC'!H19,0) -> 0.17325496 | I12: =IFERROR('HISTORICAL FC'!I19,0) -> 0.1563052 | J12: =IFERROR('HISTORICAL FC'!J19,0) -> 0.16239006 | ... L12: =IFERROR('HISTORICAL FC'!L19,0) -> 0.17199269 | N12: =IFERROR(AVERAGE(C12:L12),0) -> 0.16127229 | O12: =IFERROR(MEDIAN(C12:L12),0) -> 0.15934763
B13: EBIT Margin | C13: =IFERROR(('HISTORICAL FC'!C18-'HISTORICAL FC'!C24)/'HISTORICAL FC'!C6,0) -> 0.11085064 | D13: =IFERROR(('HISTORICAL FC'!D18-'HISTORICAL FC'!D24)/'HISTORICAL FC'!D6,0) -> 0.1140337 | E13: =IFERROR(('HISTORICAL FC'!E18-'HISTORICAL FC'!E24)/'HISTORICAL FC'!E6,0) -> 0.12181729 | F13: =IFERROR(('HISTORICAL FC'!F18-'HISTORICAL FC'!F24)/'HISTORICAL FC'!F6,0) -> 0.11140573 | G13: =IFERROR(('HISTORICAL FC'!G18-'HISTORICAL FC'!G24)/'HISTORICAL FC'!G6,0) -> 0.11239377 | H13: =IFERROR(('HISTORICAL FC'!H18-'HISTORICAL FC'!H24)/'HISTORICAL FC'!H6,0) -> 0.11627104 | I13: =IFERROR(('HISTORICAL FC'!I18-'HISTORICAL FC'!I24)/'HISTORICAL FC'!I6,0) -> 0.11343323 | J13: =IFERROR(('HISTORICAL FC'!J18-'HISTORICAL FC'!J24)/'HISTORICAL FC'!J6,0) -> 0.11640286 | ... L13: =IFERROR(('HISTORICAL FC'!L18-'HISTORICAL FC'!L24)/'HISTORICAL FC'!L6,0) -> 0.1168048 | N13: =IFERROR(AVERAGE(C13:L13),0) -> 0.11576187 | O13: =IFERROR(MEDIAN(C13:L13),0) -> 0.11515237
B14: EBT Margin | C14: =IFERROR('HISTORICAL FC'!C28,0) -> 0.09730981 | D14: =IFERROR('HISTORICAL FC'!D28,0) -> 0.1013706 | E14: =IFERROR('HISTORICAL FC'!E28,0) -> 0.10121462 | F14: =IFERROR('HISTORICAL FC'!F28,0) -> 0.08238246 | G14: =IFERROR('HISTORICAL FC'!G28,0) -> 0.075477769 | H14: =IFERROR('HISTORICAL FC'!H28,0) -> 0.070831019 | I14: =IFERROR('HISTORICAL FC'!I28,0) -> 0.092439176 | J14: =IFERROR('HISTORICAL FC'!J28,0) -> 0.09407163 | ... L14: =IFERROR('HISTORICAL FC'!L28,0) -> 0.091598637 | N14: =IFERROR(AVERAGE(C14:L14),0) -> 0.090518734 | O14: =IFERROR(MEDIAN(C14:L14),0) -> 0.093255403
B15: Net Profit Margin | C15: =IFERROR('HISTORICAL FC'!C34,0) -> 0.064747251 | D15: =IFERROR('HISTORICAL FC'!D34,0) -> 0.067809603 | E15: =IFERROR('HISTORICAL FC'!E34,0) -> 0.067066166 | F15: =IFERROR('HISTORICAL FC'!F34,0) -> 0.055303456 | G15: =IFERROR('HISTORICAL FC'!G34,0) -> 0.052473776 | H15: =IFERROR('HISTORICAL FC'!H34,0) -> 0.067138173 | I15: =IFERROR('HISTORICAL FC'!I34,0) -> 0.069449943 | J15: =IFERROR('HISTORICAL FC'!J34,0) -> 0.070821866 | ... L15: =IFERROR('HISTORICAL FC'!L34,0) -> 0.065394362 | N15: =IFERROR(AVERAGE(C15:L15),0) -> 0.065010241 | O15: =IFERROR(MEDIAN(C15:L15),0) -> 0.067102169
B17: Sales Expense % Sales | C17: =IFERROR('HISTORICAL FC'!C16,0) -> 0.057112879 | D17: =IFERROR('HISTORICAL FC'!D16,0) -> 0.05197826 | E17: =IFERROR('HISTORICAL FC'!E16,0) -> 0.06463028 | F17: =IFERROR('HISTORICAL FC'!F16,0) -> 0.084254588 | G17: =IFERROR('HISTORICAL FC'!G16,0) -> 0.10318111 | H17: =IFERROR('HISTORICAL FC'!H16,0) -> 0.12244723 | I17: =IFERROR('HISTORICAL FC'!I16,0) -> 0.092512592 | J17: =IFERROR('HISTORICAL FC'!J16,0) -> 0.086722212 | ... L17: =IFERROR('HISTORICAL FC'!L16,0) -> 0.10053073 | N17: =IFERROR(AVERAGE(C17:L17),0) -> 0.08580352 | O17: =IFERROR(MEDIAN(C17:L17),0) -> 0.089617402
B18: Depreciation % Sales | C18: =IFERROR('HISTORICAL FC'!C25,0) -> 0.042427444 | D18: =IFERROR('HISTORICAL FC'!D25,0) -> 0.038315008 | E18: =IFERROR('HISTORICAL FC'!E25,0) -> 0.042745693 | F18: =IFERROR('HISTORICAL FC'!F25,0) -> 0.03683378 | G18: =IFERROR('HISTORICAL FC'!G25,0) -> 0.037210963 | H18: =IFERROR('HISTORICAL FC'!H25,0) -> 0.056983918 | I18: =IFERROR('HISTORICAL FC'!I25,0) -> 0.04287197 | J18: =IFERROR('HISTORICAL FC'!J25,0) -> 0.045987202 | ... L18: =IFERROR('HISTORICAL FC'!L25,0) -> 0.055187886 | N18: =IFERROR(AVERAGE(C18:L18),0) -> 0.045510411 | O18: =IFERROR(MEDIAN(C18:L18),0) -> 0.042808832
B19: Operating Income % Sales | C19: =IFERROR(C12,0) -> 0.15327808 | D19: =IFERROR(D12,0) -> 0.15234871 | E19: =IFERROR(E12,0) -> 0.16456299 | F19: =IFERROR(F12,0) -> 0.14823951 | G19: =IFERROR(G12,0) -> 0.14960473 | H19: =IFERROR(H12,0) -> 0.17325496 | I19: =IFERROR(I12,0) -> 0.1563052 | J19: =IFERROR(J12,0) -> 0.16239006 | ... L19: =IFERROR(L12,0) -> 0.17199269 | N19: =IFERROR(AVERAGE(C19:L19),0) -> 0.16127229 | O19: =IFERROR(MEDIAN(C19:L19),0) -> 0.15934763
B21: Return on Capital Employed | C21: =IFERROR(('HISTORICAL FC'!C18-'HISTORICAL FC'!C24)/(SUM('HISTORICAL FC'!C49:C51)),0) -> 0.070884651 | D21: =IFERROR(('HISTORICAL FC'!D18-'HISTORICAL FC'!D24)/(SUM('HISTORICAL FC'!D49:D51)),0) -> 0.072032736 | E21: =IFERROR(('HISTORICAL FC'!E18-'HISTORICAL FC'!E24)/(SUM('HISTORICAL FC'!E49:E51)),0) -> 0.089264253 | F21: =IFERROR(('HISTORICAL FC'!F18-'HISTORICAL FC'!F24)/(SUM('HISTORICAL FC'!F49:F51)),0) -> 0.091124972 | G21: =IFERROR(('HISTORICAL FC'!G18-'HISTORICAL FC'!G24)/(SUM('HISTORICAL FC'!G49:G51)),0) -> 0.083380683 | H21: =IFERROR(('HISTORICAL FC'!H18-'HISTORICAL FC'!H24)/(SUM('HISTORICAL FC'!H49:H51)),0) -> 0.055373422 | I21: =IFERROR(('HISTORICAL FC'!I18-'HISTORICAL FC'!I24)/(SUM('HISTORICAL FC'!I49:I51)),0) -> 0.071723936 | J21: =IFERROR(('HISTORICAL FC'!J18-'HISTORICAL FC'!J24)/(SUM('HISTORICAL FC'!J49:J51)),0) -> 0.087376321 | ... L21: =IFERROR(('HISTORICAL FC'!L18-'HISTORICAL FC'!L24)/(SUM('HISTORICAL FC'!L49:L51)),0) -> 0.092370266 | N21: =IFERROR(AVERAGE(C21:L21),0) -> 0.081112432 | O21: =IFERROR(MEDIAN(C21:L21),0) -> 0.085378502
B22: Return Earnings % | C22: =IFERROR('HISTORICAL FC'!C45,0) -> 0.82461329 | D22: =IFERROR('HISTORICAL FC'!D45,0) -> 0.84207947 | E22: =IFERROR('HISTORICAL FC'!E45,0) -> 0.86443859 | F22: =IFERROR('HISTORICAL FC'!F45,0) -> 0.87744902 | G22: =IFERROR('HISTORICAL FC'!G45,0) -> 0.86840147 | H22: =IFERROR('HISTORICAL FC'!H45,0) -> 0.85589485 | I22: =IFERROR('HISTORICAL FC'!I45,0) -> 0.88782257 | J22: =IFERROR('HISTORICAL FC'!J45,0) -> 0.90189147 | ... L22: =IFERROR('HISTORICAL FC'!L45,0) -> 0.88179407 | N22: =IFERROR(AVERAGE(C22:L22),0) -> 0.86967162 | O22: =IFERROR(MEDIAN(C22:L22),0) -> 0.87292524
B23: Return on Equity % | C23: =IFERROR('HISTORICAL FC'!C33/SUM('HISTORICAL FC'!C49:C50),0) -> 0.076219144 | D23: =IFERROR('HISTORICAL FC'!D33/SUM('HISTORICAL FC'!D49:D50),0) -> 0.078158121 | E23: =IFERROR('HISTORICAL FC'!E33/SUM('HISTORICAL FC'!E49:E50),0) -> 0.089303115 | F23: =IFERROR('HISTORICAL FC'!F33/SUM('HISTORICAL FC'!F49:F50),0) -> 0.081193556 | G23: =IFERROR('HISTORICAL FC'!G33/SUM('HISTORICAL FC'!G49:G50),0) -> 0.069706968 | H23: =IFERROR('HISTORICAL FC'!H33/SUM('HISTORICAL FC'!H49:H50),0) -> 0.044713299 | I23: =IFERROR('HISTORICAL FC'!I33/SUM('HISTORICAL FC'!I49:I50),0) -> 0.06189343 | J23: =IFERROR('HISTORICAL FC'!J33/SUM('HISTORICAL FC'!J49:J50),0) -> 0.086702651 | ... L23: =IFERROR('HISTORICAL FC'!L33/SUM('HISTORICAL FC'!L49:L50),0) -> 0.07467149 | N23: =IFERROR(AVERAGE(C23:L23),0) -> 0.074175838 | O23: =IFERROR(MEDIAN(C23:L23),0) -> 0.077188632
B24: Self Sustained Growth Rate | C24: =IFERROR(C22*C23,0) -> 0.062851319 | D24: =IFERROR(D22*D23,0) -> 0.065815349 | E24: =IFERROR(E22*E23,0) -> 0.077197059 | F24: =IFERROR(F22*F23,0) -> 0.071243206 | G24: =IFERROR(G22*G23,0) -> 0.060533633 | H24: =IFERROR(H22*H23,0) -> 0.038269882 | I24: =IFERROR(I22*I23,0) -> 0.054950384 | J24: =IFERROR(J22*J23,0) -> 0.078196381 | ... L24: =IFERROR(L22*L23,0) -> 0.065844877 | N24: =IFERROR(AVERAGE(C24:L24),0) -> 0.064557171 | O24: =IFERROR(MEDIAN(C24:L24),0) -> 0.065830113
B25: Interest Coverage Ratio | C25: =IFERROR(('HISTORICAL FC'!C18-'HISTORICAL FC'!C24)/'HISTORICAL FC'!C21,0) -> 8.1863993 | D25: =IFERROR(('HISTORICAL FC'!D18-'HISTORICAL FC'!D24)/'HISTORICAL FC'!D21,0) -> 9.0051962 | E25: =IFERROR(('HISTORICAL FC'!E18-'HISTORICAL FC'!E24)/'HISTORICAL FC'!E21,0) -> 5.9126925 | F25: =IFERROR(('HISTORICAL FC'!F18-'HISTORICAL FC'!F24)/'HISTORICAL FC'!F21,0) -> 3.8384965 | G25: =IFERROR(('HISTORICAL FC'!G18-'HISTORICAL FC'!G24)/'HISTORICAL FC'!G21,0) -> 3.0445816 | H25: =IFERROR(('HISTORICAL FC'!H18-'HISTORICAL FC'!H24)/'HISTORICAL FC'!H21,0) -> 2.5587805 | I25: =IFERROR(('HISTORICAL FC'!I18-'HISTORICAL FC'!I24)/'HISTORICAL FC'!I21,0) -> 5.403113 | J25: =IFERROR(('HISTORICAL FC'!J18-'HISTORICAL FC'!J24)/'HISTORICAL FC'!J21,0) -> 5.2125594 | ... L25: =IFERROR(('HISTORICAL FC'!L18-'HISTORICAL FC'!L24)/'HISTORICAL FC'!L21,0) -> 4.6339775 | N25: =IFERROR(AVERAGE(C25:L25),0) -> 5.2626059 | O25: 0.01
B27: Debtor Turnover Ratio | C27: =IFERROR('HISTORICAL FC'!C6/'HISTORICAL FC'!C61,0) -> 61.048824 | D27: =IFERROR('HISTORICAL FC'!D6/'HISTORICAL FC'!D61,0) -> 37.171823 | E27: =IFERROR('HISTORICAL FC'!E6/'HISTORICAL FC'!E61,0) -> 22.262774 | F27: =IFERROR('HISTORICAL FC'!F6/'HISTORICAL FC'!F61,0) -> 18.888531 | G27: =IFERROR('HISTORICAL FC'!G6/'HISTORICAL FC'!G61,0) -> 30.356074 | H27: =IFERROR('HISTORICAL FC'!H6/'HISTORICAL FC'!H61,0) -> 24.524403 | I27: =IFERROR('HISTORICAL FC'!I6/'HISTORICAL FC'!I61,0) -> 29.385491 | J27: =IFERROR('HISTORICAL FC'!J6/'HISTORICAL FC'!J61,0) -> 30.806946 | ... L27: =IFERROR('HISTORICAL FC'!L6/'HISTORICAL FC'!L61,0) -> 22.858432 | N27: =IFERROR(AVERAGE(C27:L27),0) -> 30.572878 | O27: =IFERROR(MEDIAN(C27:L27),0) -> 28.905484
B28: Creditor Turnover Ratio | C28: =IFERROR('HISTORICAL FC'!C6/'HISTORICAL FC'!C52,0) -> 1.5781146 | D28: =IFERROR('HISTORICAL FC'!D6/'HISTORICAL FC'!D52,0) -> 1.3472063 | E28: =IFERROR('HISTORICAL FC'!E6/'HISTORICAL FC'!E52,0) -> 1.4062226 | F28: =IFERROR('HISTORICAL FC'!F6/'HISTORICAL FC'!F52,0) -> 1.8769138 | G28: =IFERROR('HISTORICAL FC'!G6/'HISTORICAL FC'!G52,0) -> 1.6633744 | H28: =IFERROR('HISTORICAL FC'!H6/'HISTORICAL FC'!H52,0) -> 1.367746 | I28: =IFERROR('HISTORICAL FC'!I6/'HISTORICAL FC'!I52,0) -> 1.7367737 | J28: =IFERROR('HISTORICAL FC'!J6/'HISTORICAL FC'!J52,0) -> 1.9993247 | ... L28: =IFERROR('HISTORICAL FC'!L6/'HISTORICAL FC'!L52,0) -> 1.3149686 | N28: =IFERROR(AVERAGE(C28:L28),0) -> 1.5762436 | O28: =IFERROR(MEDIAN(C28:L28),0) -> 1.5249531
B29: Inventory Turnover Ratio | C29: =IFERROR('HISTORICAL FC'!C6/'HISTORICAL FC'!C62,0) -> 5.8637654 | D29: =IFERROR('HISTORICAL FC'!D6/'HISTORICAL FC'!D62,0) -> 6.2093522 | E29: =IFERROR('HISTORICAL FC'!E6/'HISTORICAL FC'!E62,0) -> 6.4241005 | F29: =IFERROR('HISTORICAL FC'!F6/'HISTORICAL FC'!F62,0) -> 8.4122053 | G29: =IFERROR('HISTORICAL FC'!G6/'HISTORICAL FC'!G62,0) -> 8.073813 | H29: =IFERROR('HISTORICAL FC'!H6/'HISTORICAL FC'!H62,0) -> 5.7095088 | I29: =IFERROR('HISTORICAL FC'!I6/'HISTORICAL FC'!I62,0) -> 6.4454063 | J29: =IFERROR('HISTORICAL FC'!J6/'HISTORICAL FC'!J62,0) -> 6.2596137 | ... L29: =IFERROR('HISTORICAL FC'!L6/'HISTORICAL FC'!L62,0) -> 6.5918583 | N29: =IFERROR(AVERAGE(C29:L29),0) -> 6.5874555 | O29: =IFERROR(MEDIAN(C29:L29),0) -> 6.3418571
B30: Fixed Asset Turnover | C30: =IFERROR('HISTORICAL FC'!C6/'HISTORICAL FC'!C55,0) -> 1.4741388 | D30: =IFERROR('HISTORICAL FC'!D6/'HISTORICAL FC'!D55,0) -> 1.5310539 | E30: =IFERROR('HISTORICAL FC'!E6/'HISTORICAL FC'!E55,0) -> 0.96765911 | F30: =IFERROR('HISTORICAL FC'!F6/'HISTORICAL FC'!F55,0) -> 1.4266418 | G30: =IFERROR('HISTORICAL FC'!G6/'HISTORICAL FC'!G55,0) -> 1.1201916 | H30: =IFERROR('HISTORICAL FC'!H6/'HISTORICAL FC'!H55,0) -> 0.86152445 | I30: =IFERROR('HISTORICAL FC'!I6/'HISTORICAL FC'!I55,0) -> 1.1065231 | J30: =IFERROR('HISTORICAL FC'!J6/'HISTORICAL FC'!J55,0) -> 1.2091473 | ... L30: =IFERROR('HISTORICAL FC'!L6/'HISTORICAL FC'!L55,0) -> 0.96340479 | N30: =IFERROR(AVERAGE(C30:L30),0) -> 1.1812924 | O30: =IFERROR(MEDIAN(C30:L30),0) -> 1.1364152
B31: Capital Assets Turnover | C31: =IFERROR('HISTORICAL FC'!C6/SUM('HISTORICAL FC'!C49:C50),0) -> 1.1771796 | D31: =IFERROR('HISTORICAL FC'!D6/SUM('HISTORICAL FC'!D49:D50),0) -> 1.1526114 | E31: =IFERROR('HISTORICAL FC'!E6/SUM('HISTORICAL FC'!E49:E50),0) -> 1.3315673 | F31: =IFERROR('HISTORICAL FC'!F6/SUM('HISTORICAL FC'!F49:F50),0) -> 1.4681462 | G31: =IFERROR('HISTORICAL FC'!G6/SUM('HISTORICAL FC'!G49:G50),0) -> 1.3284153 | H31: =IFERROR('HISTORICAL FC'!H6/SUM('HISTORICAL FC'!H49:H50),0) -> 0.66598921 | I31: =IFERROR('HISTORICAL FC'!I6/SUM('HISTORICAL FC'!I49:I50),0) -> 0.89119483 | J31: =IFERROR('HISTORICAL FC'!J6/SUM('HISTORICAL FC'!J49:J50),0) -> 1.2242356 | ... L31: =IFERROR('HISTORICAL FC'!L6/SUM('HISTORICAL FC'!L49:L50),0) -> 1.1418643 | N31: =IFERROR(AVERAGE(C31:L31),0) -> 1.1514238 | O31: =IFERROR(MEDIAN(C31:L31),0) -> 1.1648955
B33: Debtor Days | C33: =IFERROR(365/C27,0) -> 5.9788211 | D33: =IFERROR(365/D27,0) -> 9.8192654 | E33: =IFERROR(365/E27,0) -> 16.395082 | F33: =IFERROR(365/F27,0) -> 19.323896 | G33: =IFERROR(365/G27,0) -> 12.023953 | H33: =IFERROR(365/H27,0) -> 14.883135 | I33: =IFERROR(365/I27,0) -> 12.421096 | J33: =IFERROR(365/J27,0) -> 11.847977 | ... L33: =IFERROR(365/L27,0) -> 15.96785 | N33: =IFERROR(AVERAGE(C33:L33),0) -> 13.150167 | O33: =IFERROR(MEDIAN(C33:L33),0) -> 12.630845
B34: Payable Days | C34: =IFERROR(365/C28,0) -> 231.28865 | D34: =IFERROR(365/D28,0) -> 270.93103 | E34: =IFERROR(365/E28,0) -> 259.56062 | F34: =IFERROR(365/F28,0) -> 194.46818 | G34: =IFERROR(365/G28,0) -> 219.43346 | H34: =IFERROR(365/H28,0) -> 266.86242 | I34: =IFERROR(365/I28,0) -> 210.15979 | J34: =IFERROR(365/J28,0) -> 182.56164 | ... L34: =IFERROR(365/L28,0) -> 277.57317 | N34: =IFERROR(AVERAGE(C34:L34),0) -> 236.0836 | O34: =IFERROR(MEDIAN(C34:L34),0) -> 239.64285
B35: Inventory Days | C35: =IFERROR(365/C29,0) -> 62.246692 | D35: =IFERROR(365/D29,0) -> 58.782299 | E35: =IFERROR(365/E29,0) -> 56.817293 | F35: =IFERROR(365/F29,0) -> 43.389336 | G35: =IFERROR(365/G29,0) -> 45.207884 | H35: =IFERROR(365/H29,0) -> 63.928442 | I35: =IFERROR(365/I29,0) -> 56.629479 | J35: =IFERROR(365/J29,0) -> 58.310307 | ... L35: =IFERROR(365/L29,0) -> 55.371336 | N35: =IFERROR(AVERAGE(C35:L35),0) -> 56.270588 | O35: =IFERROR(MEDIAN(C35:L35),0) -> 57.5638
B36: Cash Inversion Cycle | C36: =IFERROR(C33+C35-C34,0) -> -163.06314 | D36: =IFERROR(D33+D35-D34,0) -> -202.32946 | E36: =IFERROR(E33+E35-E34,0) -> -186.34824 | F36: =IFERROR(F33+F35-F34,0) -> -131.75494 | G36: =IFERROR(G33+G35-G34,0) -> -162.20163 | H36: =IFERROR(H33+H35-H34,0) -> -188.05084 | I36: =IFERROR(I33+I35-I34,0) -> -141.10922 | J36: =IFERROR(J33+J35-J34,0) -> -112.40335 | ... L36: =IFERROR(L33+L35-L34,0) -> -206.23398 | N36: =IFERROR(AVERAGE(C36:L36),0) -> -166.66285 | O36: =IFERROR(MEDIAN(C36:L36),0) -> -168.0984
B38: CFO/Sales | C38: =IFERROR('HISTORICAL FC'!C78/'HISTORICAL FC'!C6,0) -> 0.1686202 | D38: =IFERROR('HISTORICAL FC'!D78/'HISTORICAL FC'!D6,0) -> 0.21389092 | E38: =IFERROR('HISTORICAL FC'!E78/'HISTORICAL FC'!E6,0) -> 0.2302756 | F38: =IFERROR('HISTORICAL FC'!F78/'HISTORICAL FC'!F6,0) -> 0.023866122 | G38: =IFERROR('HISTORICAL FC'!G78/'HISTORICAL FC'!G6,0) -> 0.18903464 | H38: =IFERROR('HISTORICAL FC'!H78/'HISTORICAL FC'!H6,0) -> -0.049323729 | I38: =IFERROR('HISTORICAL FC'!I78/'HISTORICAL FC'!I6,0) -> 0.16033299 | J38: =IFERROR('HISTORICAL FC'!J78/'HISTORICAL FC'!J6,0) -> 0.10885262 | ... L38: =IFERROR('HISTORICAL FC'!L78/'HISTORICAL FC'!L6,0) -> 0.21024387 | N38: =IFERROR(AVERAGE(C38:L38),0) -> 0.14394934 | O38: =IFERROR(MEDIAN(C38:L38),0) -> 0.17616019
B39: CFO/Total Assets | C39: =IFERROR('HISTORICAL FC'!C78/'HISTORICAL FC'!C66,0) -> 0.076733272 | D39: =IFERROR('HISTORICAL FC'!D78/'HISTORICAL FC'!D66,0) -> 0.091981913 | E39: =IFERROR('HISTORICAL FC'!E78/'HISTORICAL FC'!E66,0) -> 0.11093306 | F39: =IFERROR('HISTORICAL FC'!F78/'HISTORICAL FC'!F66,0) -> 0.013596223 | G39: =IFERROR('HISTORICAL FC'!G78/'HISTORICAL FC'!G66,0) -> 0.096983272 | H39: =IFERROR('HISTORICAL FC'!H78/'HISTORICAL FC'!H66,0) -> -0.017423384 | I39: =IFERROR('HISTORICAL FC'!I78/'HISTORICAL FC'!I66,0) -> 0.074320943 | J39: =IFERROR('HISTORICAL FC'!J78/'HISTORICAL FC'!J66,0) -> 0.059405361 | ... L39: =IFERROR('HISTORICAL FC'!L78/'HISTORICAL FC'!L66,0) -> 0.103824 | N39: =IFERROR(AVERAGE(C39:L39),0) -> 0.070445693 | O39: =IFERROR(MEDIAN(C39:L39),0) -> 0.084357593
B40: CFO/Total Debt | C40: =IFERROR('HISTORICAL FC'!C78/'HISTORICAL FC'!C51,0) -> 0.2360539 | D40: =IFERROR('HISTORICAL FC'!D78/'HISTORICAL FC'!D51,0) -> 0.29894471 | E40: =IFERROR('HISTORICAL FC'!E78/'HISTORICAL FC'!E51,0) -> 0.37523296 | F40: =IFERROR('HISTORICAL FC'!F78/'HISTORICAL FC'!F51,0) -> 0.044079892 | G40: =IFERROR('HISTORICAL FC'!G78/'HISTORICAL FC'!G51,0) -> 0.31760777 | H40: =IFERROR('HISTORICAL FC'!H78/'HISTORICAL FC'!H51,0) -> -0.082448506 | I40: =IFERROR('HISTORICAL FC'!I78/'HISTORICAL FC'!I51,0) -> 0.34897762 | J40: =IFERROR('HISTORICAL FC'!J78/'HISTORICAL FC'!J51,0) -> 0.21121453 | ... L40: =IFERROR('HISTORICAL FC'!L78/'HISTORICAL FC'!L51,0) -> 0.54079607 | N40: =IFERROR(AVERAGE(C40:L40),0) -> 0.27613602 | O40: =IFERROR(MEDIAN(C40:L40),0) -> 0.30827624
B42: Return On Asset
B43: PAT vs Total Assets | C43: =IFERROR('HISTORICAL FC'!C33/'HISTORICAL FC'!C66,0) -> 0.029464254 | D43: =IFERROR('HISTORICAL FC'!D33/'HISTORICAL FC'!D66,0) -> 0.029160925 | E43: =IFERROR('HISTORICAL FC'!E33/'HISTORICAL FC'!E66,0) -> 0.032308483 | F43: =IFERROR('HISTORICAL FC'!F33/'HISTORICAL FC'!F66,0) -> 0.031505668 | G43: =IFERROR('HISTORICAL FC'!G33/'HISTORICAL FC'!G66,0) -> 0.026921407 | H43: =IFERROR('HISTORICAL FC'!H33/'HISTORICAL FC'!H66,0) -> 0.023716256 | I43: =IFERROR('HISTORICAL FC'!I33/'HISTORICAL FC'!I66,0) -> 0.032192908 | J43: =IFERROR('HISTORICAL FC'!J33/'HISTORICAL FC'!J66,0) -> 0.038650411 | ... L43: =IFERROR('HISTORICAL FC'!L33/'HISTORICAL FC'!L66,0) -> 0.032293471 | N43: =IFERROR(AVERAGE(C43:L43),0) -> 0.031201964 | O43: =IFERROR(MEDIAN(C43:L43),0) -> 0.031849288
B44: EBIT vs Total Assets | C44: =IFERROR(('HISTORICAL FC'!C18-'HISTORICAL FC'!C24)/'HISTORICAL FC'!C66,0) -> 0.050444326 | D44: =IFERROR(('HISTORICAL FC'!D18-'HISTORICAL FC'!D24)/'HISTORICAL FC'!D66,0) -> 0.049039193 | E44: =IFERROR(('HISTORICAL FC'!E18-'HISTORICAL FC'!E24)/'HISTORICAL FC'!E66,0) -> 0.058684315 | F44: =IFERROR(('HISTORICAL FC'!F18-'HISTORICAL FC'!F24)/'HISTORICAL FC'!F66,0) -> 0.063466415 | G44: =IFERROR(('HISTORICAL FC'!G18-'HISTORICAL FC'!G24)/'HISTORICAL FC'!G66,0) -> 0.057663057 | H44: =IFERROR(('HISTORICAL FC'!H18-'HISTORICAL FC'!H24)/'HISTORICAL FC'!H66,0) -> 0.04107222 | I44: =IFERROR(('HISTORICAL FC'!I18-'HISTORICAL FC'!I24)/'HISTORICAL FC'!I66,0) -> 0.052580971 | J44: =IFERROR(('HISTORICAL FC'!J18-'HISTORICAL FC'!J24)/'HISTORICAL FC'!J66,0) -> 0.063525838 | ... L44: =IFERROR(('HISTORICAL FC'!L18-'HISTORICAL FC'!L24)/'HISTORICAL FC'!L66,0) -> 0.05768131 | N44: =IFERROR(AVERAGE(C44:L44),0) -> 0.055778326 | O44: =IFERROR(MEDIAN(C44:L44),0) -> 0.057672183
B45: PATafter TAX Benefit vs Total Assets | C45: =IFERROR((('HISTORICAL FC'!C18-'HISTORICAL FC'!C24)-('HISTORICAL FC'!C21-('HISTORICAL FC'!C21*'HISTORICAL FC'!C31)))/'HISTORICAL FC'!C66,0) -> 0.046344324 | D45: =IFERROR((('HISTORICAL FC'!D18-'HISTORICAL FC'!D24)-('HISTORICAL FC'!D21-('HISTORICAL FC'!D21*'HISTORICAL FC'!D31)))/'HISTORICAL FC'!D66,0) -> 0.045396444 | E45: =IFERROR((('HISTORICAL FC'!E18-'HISTORICAL FC'!E24)-('HISTORICAL FC'!E21-('HISTORICAL FC'!E21*'HISTORICAL FC'!E31)))/'HISTORICAL FC'!E66,0) -> 0.052107782 | F45: =IFERROR((('HISTORICAL FC'!F18-'HISTORICAL FC'!F24)-('HISTORICAL FC'!F21-('HISTORICAL FC'!F21*'HISTORICAL FC'!F31)))/'HISTORICAL FC'!F66,0) -> 0.052366994 | G45: =IFERROR((('HISTORICAL FC'!G18-'HISTORICAL FC'!G24)-('HISTORICAL FC'!G21-('HISTORICAL FC'!G21*'HISTORICAL FC'!G31)))/'HISTORICAL FC'!G66,0) -> 0.044495861 | H45: =IFERROR((('HISTORICAL FC'!H18-'HISTORICAL FC'!H24)-('HISTORICAL FC'!H21-('HISTORICAL FC'!H21*'HISTORICAL FC'!H31)))/'HISTORICAL FC'!H66,0) -> 0.025857598 | I45: =IFERROR((('HISTORICAL FC'!I18-'HISTORICAL FC'!I24)-('HISTORICAL FC'!I21-('HISTORICAL FC'!I21*'HISTORICAL FC'!I31)))/'HISTORICAL FC'!I66,0) -> 0.045269574 | J45: =IFERROR((('HISTORICAL FC'!J18-'HISTORICAL FC'!J24)-('HISTORICAL FC'!J21-('HISTORICAL FC'!J21*'HISTORICAL FC'!J31)))/'HISTORICAL FC'!J66,0) -> 0.054350796 | ... L45: =IFERROR((('HISTORICAL FC'!L18-'HISTORICAL FC'!L24)-('HISTORICAL FC'!L21-('HISTORICAL FC'!L21*'HISTORICAL FC'!L31)))/'HISTORICAL FC'!L66,0) -> 0.048794774 | N45: =IFERROR(AVERAGE(C45:L45),0) -> 0.046926161 | O45: =IFERROR(MEDIAN(C45:L45),0) -> 0.047569549
B47: Return On Equity
B48: EPS | C48: =IFERROR('HISTORICAL FC'!C39,0) -> 12.765265 | D48: =IFERROR('HISTORICAL FC'!D39,0) -> 14.857773 | E48: =IFERROR('HISTORICAL FC'!E39,0) -> 19.395585 | F48: =IFERROR('HISTORICAL FC'!F39,0) -> 23.243311 | G48: =IFERROR('HISTORICAL FC'!G39,0) -> 23.151948 | H48: =IFERROR('HISTORICAL FC'!H39,0) -> 24.692205 | I48: =IFERROR('HISTORICAL FC'!I39,0) -> 35.658325 | J48: =IFERROR('HISTORICAL FC'!J39,0) -> 45.870285 | ... L48: =IFERROR('HISTORICAL FC'!L39,0) -> 46.527593 | N48: =IFERROR(AVERAGE(C48:L48),0) -> 29.260316 | O48: =IFERROR(MEDIAN(C48:L48),0) -> 23.967758
B49: Cash Flow EPS | C49: =IFERROR(('HISTORICAL FC'!C33+'HISTORICAL FC'!C24)/'HISTORICAL FC'!C36,0) -> 21.130061 | D49: =IFERROR(('HISTORICAL FC'!D33+'HISTORICAL FC'!D24)/'HISTORICAL FC'!D36,0) -> 23.252981 | E49: =IFERROR(('HISTORICAL FC'!E33+'HISTORICAL FC'!E24)/'HISTORICAL FC'!E36,0) -> 31.757672 | F49: =IFERROR(('HISTORICAL FC'!F33+'HISTORICAL FC'!F24)/'HISTORICAL FC'!F36,0) -> 38.724062 | G49: =IFERROR(('HISTORICAL FC'!G33+'HISTORICAL FC'!G24)/'HISTORICAL FC'!G36,0) -> 39.569792 | H49: =IFERROR(('HISTORICAL FC'!H33+'HISTORICAL FC'!H24)/'HISTORICAL FC'!H36,0) -> 45.649859 | I49: =IFERROR(('HISTORICAL FC'!I33+'HISTORICAL FC'!I24)/'HISTORICAL FC'!I36,0) -> 57.670476 | J49: =IFERROR(('HISTORICAL FC'!J33+'HISTORICAL FC'!J24)/'HISTORICAL FC'!J36,0) -> 75.655522 | ... L49: =IFERROR(('HISTORICAL FC'!L33+'HISTORICAL FC'!L24)/'HISTORICAL FC'!L36,0) -> 85.793355 | N49: =IFERROR(AVERAGE(C49:L49),0) -> 50.321061 | O49: =IFERROR(MEDIAN(C49:L49),0) -> 42.609826
B50: DPS | C50: =IFERROR('HISTORICAL FC'!C42,0) -> 2.2388578 | D50: =IFERROR('HISTORICAL FC'!D42,0) -> 2.3463474 | E50: =IFERROR('HISTORICAL FC'!E42,0) -> 2.6292928 | F50: =IFERROR('HISTORICAL FC'!F42,0) -> 2.8484907 | G50: =IFERROR('HISTORICAL FC'!G42,0) -> 3.0467624 | H50: =IFERROR('HISTORICAL FC'!H42,0) -> 3.558274 | I50: =IFERROR('HISTORICAL FC'!I42,0) -> 4.0000591 | J50: =IFERROR('HISTORICAL FC'!J42,0) -> 4.5002661 | ... L50: =IFERROR('HISTORICAL FC'!L42,0) -> 5.4998374 | N50: =IFERROR(AVERAGE(C50:L50),0) -> 3.5668409 | O50: =IFERROR(MEDIAN(C50:L50),0) -> 3.3025182
B51: Dividend Payout Ratio | C51: =IFERROR('HISTORICAL FC'!C43,0) -> 0.17538671 | D51: =IFERROR('HISTORICAL FC'!D43,0) -> 0.15792053 | E51: =IFERROR('HISTORICAL FC'!E43,0) -> 0.13556141 | F51: =IFERROR('HISTORICAL FC'!F43,0) -> 0.12255098 | G51: =IFERROR('HISTORICAL FC'!G43,0) -> 0.13159853 | H51: =IFERROR('HISTORICAL FC'!H43,0) -> 0.14410515 | I51: =IFERROR('HISTORICAL FC'!I43,0) -> 0.11217743 | J51: =IFERROR('HISTORICAL FC'!J43,0) -> 0.098108526 | ... L51: =IFERROR('HISTORICAL FC'!L43,0) -> 0.11820593 | N51: =IFERROR(AVERAGE(C51:L51),0) -> 0.13032838 | O51: =IFERROR(MEDIAN(C51:L51),0) -> 0.12707476
B52: Dividend Yield Ratio | C52: =IFERROR(C50/'Data Sheet'!B8,0) -> 0.0016401889 | D52: =IFERROR(D50/'Data Sheet'!C8,0) -> 0 | E52: =IFERROR(E50/'Data Sheet'!D8,0) -> 0 | F52: =IFERROR(F50/'Data Sheet'!E8,0) -> 0 | G52: =IFERROR(G50/'Data Sheet'!F8,0) -> 0 | H52: =IFERROR(H50/'Data Sheet'!G8,0) -> 0 | I52: =IFERROR(I50/'Data Sheet'!H8,0) -> 0 | J52: =IFERROR(J50/'Data Sheet'!I8,0) -> 0 | ... L52: =IFERROR(L50/'Data Sheet'!K8,0) -> 0 | N52: =IFERROR(AVERAGE(C52:L52),0) -> 0.00016401889 | O52: =IFERROR(MEDIAN(C52:L52),0) -> 0

Sheet CFS
C2: 42064 | D2: 42430 | E2: 42795 | F2: 43160 | G2: 43525 | H2: 43891 | I2: 44256 | J2: 44621 | K2: 44986 | L2: 45352 | M2: 45717 | N2: 46082
B3: Cash from Operating Activity - | C3: 34374 | D3: 38134 | E3: 49550 | F3: 71459 | G3: 42346 | H3: 94877 | I3: 26958 | J3: 110654 | K3: 115032 | L3: 158788 | M3: 178703 | N3: 192113
B4: Profit from operations | C4: 38994 | D4: 38887 | E4: 44170 | F4: 62765 | G4: 83319 | H4: 85347 | I4: 80129 | J4: 113726 | K4: 140963 | L4: 164383 | M4: 166904 | N4: 189224
B5: Receivables | C5: 1097 | D5: -6880 | E5: -8511 | F5: -21991 | G5: -40136 | H5: -13792 | I5: 959 | J5: -14180 | K5: 13194 | L5: -15674 | M5: -17837 | N5: -53322
B6: Inventory | C6: 3472 | D6: 6758 | E6: -6899 | F6: -10474 | G6: -6724 | H6: -6342 | I6: -7769 | J6: -24983 | K6: -32228 | L6: -12756 | M6: 3134 | N6: -20790
B7: Payables | C7: -2754 | D7: 7951 | E7: 30873 | F7: 51003 | G7: 18078 | H7: 38050 | I7: -43148 | J7: 39888 | K7: -600 | L7: 34796 | M7: 38427 | N7: 86609
B8: Working capital changes | C8: 1815 | D8: 7829 | E8: 15463 | F8: 18538 | G8: -28782 | H8: 17916 | I8: -49958 | J8: 725 | K8: -19634 | L8: 6366 | M8: 23724 | N8: 12497
B9: Direct taxes | C9: -6435 | D9: -8582 | E9: -10083 | F9: -9844 | G9: -12191 | H9: -8386 | I9: -3213 | J9: -3797 | K9: -6297 | L9: -11961 | M9: -11925 | N9: -9608
B10: Cash from Investing Activity - | C10: -64706 | D10: -36186 | E10: -66201 | F10: -68192 | G10: -94507 | H10: -72497 | I10: -142385 | J10: -109162 | K10: -93001 | L10: -113581 | M10: -137535 | N10: -101089
B11: Fixed assets purchased | C11: -63364 | D11: -46898 | E11: -78109 | F11: -73953 | G11: -93626 | H11: -76517 | I11: -105837 | J11: -100145 | K11: -140988 | L11: -152883 | M11: -139967 | N11: -122916
B12: Fixed assets sold | C12: 402 | D12: 344 | E12: 1482 | F12: 999 | G12: 849 | H12: 964 | I12: 2319 | J12: 3137 | K12: 9186 | L12: 15307 | M12: 2343 | N12: 826
B13: Investments purchased | C13: -678241 | D13: -715334 | E13: -654760 | F13: -533984 | G13: -1107439 | H13: -1156843 | I13: -689866 | J13: -667878 | K13: -471822 | L13: -513660 | M13: -684340 | N13: -988777
B14: Investments sold | C14: 666383 | D14: 721182 | E14: 663990 | F14: 537504 | G14: 1103615 | H14: 1174796 | I14: 642551 | J14: 668137 | K14: 501266 | L14: 531355 | M14: 672558 | N14: 991876
... B29: CFO/OP | C29: 1.09 | D29: 1.12 | E29: 1.29 | F29: 1.26 | G29: 0.65 | H29: 1.16 | I29: 0.37 | J29: 1.05 | K29: 0.85 | L29: 1.05 | M29: 1.15 | N29: 1.13
C30: =SUM(C3:C29) -> -92435.91 | D30: =SUM(D3:D29) -> -4375.88 | E30: =SUM(E3:E29) -> -35714.71 | F30: =SUM(F3:F29) -> 20842.26 | G30: =SUM(G3:G29) -> -67977.35 | H30: =SUM(H3:H29) -> 96758.16 | I30: =SUM(I3:I29) -> -167086.63 | J30: =SUM(J3:J29) -> 70715.05 | ... N30: =SUM(N3:N29) -> 200946.13

Sheet DATA
B2: Weighted Average Cost Of Capital
B4: All figures are in INR unless otherwise stated
B6: Peer Comps
I7: Debt/ | J7: Debt/ | K7: Levered | L7: Unlevered
B8: Name of the Comp | E8: Country | F8: Total Debt | G8: Total Equity | H8: Tax Rate 1 | I8: Equity | J8: Capital | K8: Beta 2 | L8: Beta 3
B10: Reliance Industries | E10: India | F10: 1139 | G10: 611503.9 | H10: 0.3 | I10: =F10/G10 -> 0.001862621 | J10: =F10/(F10+G10) -> 0.0018591581 | K10: 1 | L10: =K10/(1+(1-H10)*I10) -> 0.99869786
B11: Adani Enterprises Ltd | E11: India | F11: 279.9 | G11: 182975 | H11: 0.3 | I11: =F11/G11 -> 0.0015297172 | J11: =F11/(F11+G11) -> 0.0015273807 | K11: 1 | L11: =K11/(1+(1-H11)*I11) -> 0.99893034
B12: ONGC (Oil and Natural Gas Corporation) | E12: India | F12: 3037.7 | G12: 110690 | H12: 0.3 | I12: =F12/G12 -> 0.02744331 | J12: =F12/(F12+G12) -> 0.026710291 | K12: 1 | L12: =K12/(1+(1-H12)*I12) -> 0.98115176
B13: Bharti Airtel Ltd. | E13: India | F13: 1164.5 | G13: 96254.4 | H13: 0.3 | I13: =F13/G13 -> 0.012098148 | J13: =F13/(F13+G13) -> 0.011953533 | K13: 1 | L13: =K13/(1+(1-H13)*I13) -> 0.99160241
B14: Avenue Supermarts (DMart) | E14: India | F14: 1068.1 | G14: 94940.4 | H14: 0.3 | I14: =F14/G14 -> 0.011250216 | J14: =F14/(F14+G14) -> 0.011125057 | K14: 1 | L14: =K14/(1+(1-H14)*I14) -> 0.99218638
G16: Average | H16: =AVERAGE(H10:H14) -> 0.3 | I16: =AVERAGE(I10:I14) -> 0.010836802 | J16: =AVERAGE(J10:J14) -> 0.010635084 | K16: =AVERAGE(K10:K14) -> 1 | L16: =AVERAGE(L10:L14) -> 0.99251375
G17: Median | H17: =MEDIAN(H10:H14) -> 0.3 | I17: =MEDIAN(I10:I14) -> 0.011250216 | J17: =MEDIAN(J10:J14) -> 0.011125057 | K17: =MEDIAN(K10:K14) -> 1 | L17: =MEDIAN(L10:L14) -> 0.99218638
B20: Cost Of Debt | H20: Cost Of Equity
B22: Pre Tax Cost Of Debt | E22: 0.084 | H22: Risk Free Rate | L22: 0.065
B23: Tax Rate | E23: 0.3 | H23: Equity Risk Premium | L23: 0.08
B24: Post Tax Cost Of Debt | E24: =E22*(1-E23) -> 0.0588 | H24: Levered Beta 4 | L24: =L33 -> 1.505535
H25: Cost Of Equity | L25: =L22+L23*L24 -> 0.1854428
B28: Capital Structure | H28: Levered Beta
D30: Current | E30: Target | H30: Comps Beta Unlevered Beta | L30: =L17 -> 0.99218638
B31: Total Debt | C31: 17440 | D31: =C31/$C$33 -> 0.34806905 | E31: 0.425 | H31: Target Debt/Equity | L31: =E35 -> 0.73913043
B32: Market Captialization | C32: 32665 | D32: =C32/$C$33 -> 0.65193095 | E32: =E33-E31 -> 0.575 | H32: Tax Rate | L32: =E23 -> 0.3
B33: Total Capital | C33: =C31+C32 -> 50105 | D33: =C33/$C$33 -> 1 | E33: 1 | H33: Levered Beta | L33: =L30*(1+(1-L32)*L31) -> 1.505535
B35: Debt/Equity | D35: =D31/D32 -> 0.53390479 | E35: =E31/E32 -> 0.73913043 | H35: Weighted Average Cost Of Capital
K37: Total Cost | L37: Total Weight
B38: Notes: | H38: Debt | K38: =E24 -> 0.0588 | L38: =E31 -> 0.425
B39: 1.Tax Rate considered as Marginal Tax Rate for the country | H39: Equity | K39: =L25 -> 0.1854428 | L39: =E32 -> 0.575
B40: 2 .Levered Beta is based on 5 Year Monthly Data | H40: Weighted Average Cost of Capital | L40: =SUMPRODUCT(K38:K39,L38:L39) -> 0.13161961
B41: 3. Unlevered Beta = Levered Beta /(1+ (1-Tax Rate )*Debt/Equity)
B42: 4.Levered Beta = Unlevered Beta *(1+(1-Tax Rate)*Debt/Equity)

Sheet Profit & Loss
A1: ='Data Sheet'!B1 -> RELIANCE INDUSTRIES LTD | H1: =UPDATE | M1: SCREENER.IN
A3: Narration | B3: ='Data Sheet'!B16 -> 42460 | C3: ='Data Sheet'!C16 -> 42825 | D3: ='Data Sheet'!D16 -> 43190 | E3: ='Data Sheet'!E16 -> 43555 | F3: ='Data Sheet'!F16 -> 43921 | G3: ='Data Sheet'!G16 -> 44286 | H3: ='Data Sheet'!H16 -> 44651 | I3: ='Data Sheet'!I16 -> 45016 | ... K3: ='Data Sheet'!K16 -> 45747 | L3: Trailing | M3: Best Case | N3: Worst Case
A4: Sales | B4: ='Data Sheet'!B17 -> 272583 | C4: ='Data Sheet'!C17 -> 303954 | D4: ='Data Sheet'!D17 -> 390823 | E4: ='Data Sheet'!E17 -> 568337 | F4: ='Data Sheet'!F17 -> 596679 | G4: ='Data Sheet'!G17 -> 466307 | H4: ='Data Sheet'!H17 -> 694673 | I4: ='Data Sheet'!I17 -> 876396 | ... K4: ='Data Sheet'!K17 -> 962820 | L4: =SUM(Quarters!H4:K4) -> 1024548 | M4: =$K4+M23*K4 -> 1073494.9 | N4: =$K4+N23*L4 -> 1035502.6
A5: Expenses | B5: =SUM('Data Sheet'!B18,'Data Sheet'!B20:B24, -1*'Data Sheet'!B19) -> 230802 | C5: =SUM('Data Sheet'!C18,'Data Sheet'!C20:C24, -1*'Data Sheet'!C19) -> 257647 | D5: =SUM('Data Sheet'!D18,'Data Sheet'!D20:D24, -1*'Data Sheet'!D19) -> 326508 | E5: =SUM('Data Sheet'!E18,'Data Sheet'!E20:E24, -1*'Data Sheet'!E19) -> 484087 | F5: =SUM('Data Sheet'!F18,'Data Sheet'!F20:F24, -1*'Data Sheet'!F19) -> 507413 | G5: =SUM('Data Sheet'!G18,'Data Sheet'!G20:G24, -1*'Data Sheet'!G19) -> 385517 | H5: =SUM('Data Sheet'!H18,'Data Sheet'!H20:H24, -1*'Data Sheet'!H19) -> 586092 | I5: =SUM('Data Sheet'!I18,'Data Sheet'!I20:I24, -1*'Data Sheet'!I19) -> 734078 | ... K5: =SUM('Data Sheet'!K18,'Data Sheet'!K20:K24, -1*'Data Sheet'!K19) -> 797222 | L5: =SUM(Quarters!H5:K5) -> 845908 | M5: =M4-M6 -> 886320.55 | N5: =N4-N6 -> 866277.72
A6: Operating Profit | B6: =B4-B5 -> 41781 | C6: =C4-C5 -> 46307 | D6: =D4-D5 -> 64315 | E6: =E4-E5 -> 84250 | F6: =F4-F5 -> 89266 | G6: =G4-G5 -> 80790 | H6: =H4-H5 -> 108581 | I6: =I4-I5 -> 142318 | ... K6: =K4-K5 -> 165598 | L6: =SUM(Quarters!H6:K6) -> 178640 | M6: =M4*M24 -> 187174.38 | N6: =N4*N24 -> 169224.89
A7: Other Income | B7: ='Data Sheet'!B25 -> 12212 | C7: ='Data Sheet'!C25 -> 9222 | D7: ='Data Sheet'!D25 -> 9869 | E7: ='Data Sheet'!E25 -> 8406 | F7: ='Data Sheet'!F25 -> 8570 | G7: ='Data Sheet'!G25 -> 22432 | H7: ='Data Sheet'!H25 -> 19600 | I7: ='Data Sheet'!I25 -> 12020 | ... K7: ='Data Sheet'!K25 -> 17824 | L7: =SUM(Quarters!H7:K7) -> 29420 | M7: 0 | N7: 0
A8: Depreciation | B8: ='Data Sheet'!B26 -> 11565 | C8: ='Data Sheet'!C26 -> 11646 | D8: ='Data Sheet'!D26 -> 16706 | E8: ='Data Sheet'!E26 -> 20934 | F8: ='Data Sheet'!F26 -> 22203 | G8: ='Data Sheet'!G26 -> 26572 | H8: ='Data Sheet'!H26 -> 29782 | I8: ='Data Sheet'!I26 -> 40303 | ... K8: ='Data Sheet'!K26 -> 53136 | L8: =SUM(Quarters!H8:K8) -> 56359 | M8: =+$L8 -> 56359 | N8: =+$L8 -> 56359
A9: Interest | B9: ='Data Sheet'!B27 -> 3691 | C9: ='Data Sheet'!C27 -> 3849 | D9: ='Data Sheet'!D27 -> 8052 | E9: ='Data Sheet'!E27 -> 16495 | F9: ='Data Sheet'!F27 -> 22027 | G9: ='Data Sheet'!G27 -> 21189 | H9: ='Data Sheet'!H27 -> 14584 | I9: ='Data Sheet'!I27 -> 19571 | ... K9: ='Data Sheet'!K27 -> 24269 | L9: =SUM(Quarters!H9:K9) -> 26631 | M9: =+$L9 -> 26631 | N9: =+$L9 -> 26631
A10: Profit before tax | B10: ='Data Sheet'!B28 -> 38737 | C10: ='Data Sheet'!C28 -> 40034 | D10: ='Data Sheet'!D28 -> 49426 | E10: ='Data Sheet'!E28 -> 55227 | F10: ='Data Sheet'!F28 -> 53606 | G10: ='Data Sheet'!G28 -> 55461 | H10: ='Data Sheet'!H28 -> 83815 | I10: ='Data Sheet'!I28 -> 94464 | ... K10: ='Data Sheet'!K28 -> 106017 | L10: =SUM(Quarters!H10:K10) -> 125070 | M10: =M6+M7-SUM(M8:M9) -> 104184.38 | N10: =N6+N7-SUM(N8:N9) -> 86234.893
A11: Tax | B11: ='Data Sheet'!B29 -> 8876 | C11: ='Data Sheet'!C29 -> 10201 | D11: ='Data Sheet'!D29 -> 13346 | E11: ='Data Sheet'!E29 -> 15390 | F11: ='Data Sheet'!F29 -> 13726 | G11: ='Data Sheet'!G29 -> 1722 | H11: ='Data Sheet'!H29 -> 15970 | I11: ='Data Sheet'!I29 -> 20376 | ... K11: ='Data Sheet'!K29 -> 25230 | L11: =SUM(Quarters!H11:K11) -> 27642 | M11: =IF($L10>0,$L11/$L10,0) -> 0.22101223 | N11: =IF($L10>0,$L11/$L10,0) -> 0.22101223
A12: Net profit | B12: ='Data Sheet'!B30 -> 29745 | C12: ='Data Sheet'!C30 -> 29901 | D12: ='Data Sheet'!D30 -> 36075 | E12: ='Data Sheet'!E30 -> 39588 | F12: ='Data Sheet'!F30 -> 39354 | G12: ='Data Sheet'!G30 -> 49128 | H12: ='Data Sheet'!H30 -> 60705 | I12: ='Data Sheet'!I30 -> 66702 | ... K12: ='Data Sheet'!K30 -> 69648 | L12: =SUM(Quarters!H12:K12) -> 83211 | M12: =M10-M11*M10 -> 81158.356 | N12: =N10-N11*N10 -> 67175.927
A13: EPS | B13: =IF('Data Sheet'!B93>0,B12/'Data Sheet'!B93,0) -> 21.514126 | C13: =IF('Data Sheet'!C93>0,C12/'Data Sheet'!C93,0) -> 21.55462 | D13: =IF('Data Sheet'!D93>0,D12/'Data Sheet'!D93,0) -> 26.694737 | E13: =IF('Data Sheet'!E93>0,E12/'Data Sheet'!E93,0) -> 29.275435 | F13: =IF('Data Sheet'!F93>0,F12/'Data Sheet'!F93,0) -> 29.100024 | G13: =IF('Data Sheet'!G93>0,G12/'Data Sheet'!G93,0) -> 38.747841 | H13: =IF('Data Sheet'!H93>0,H12/'Data Sheet'!H93,0) -> 44.867626 | I13: =IF('Data Sheet'!I93>0,I12/'Data Sheet'!I93,0) -> 49.294963 | ... K13: =IF('Data Sheet'!K93>0,K12/'Data Sheet'!K93,0) -> 51.467589 | L13: =IF('Data Sheet'!$B6>0,'Profit & Loss'!L12/'Data Sheet'!$B6,0) -> 61.489588 | M13: =IF('Data Sheet'!$B6>0,'Profit & Loss'!M12/'Data Sheet'!$B6,0) -> 59.972766 | N13: =IF('Data Sheet'!$B6>0,'Profit & Loss'!N12/'Data Sheet'!$B6,0) -> 49.640313
A14: Price to earning | B14: =IF(B15>0,B15/B13,"") -> 11.037399 | C14: =IF(C15>0,C15/C13,"") -> 13.922305 | D14: =IF(D15>0,D15/D13,"") -> 15.024685 | E14: =IF(E15>0,E15/E13,"") -> 21.158695 | F14: =IF(F15>0,F15/F13,"") -> 17.390363 | G14: =IF(G15>0,G15/G13,"") -> 23.711773 | H14: =IF(H15>0,H15/H13,"") -> 26.935011 | I14: =IF(I15>0,I15/I13,"") -> 21.690046 | ... K14: =IF(K15>0,K15/K13,"") -> 24.774815 | L14: =IF(L13>0,L15/L13,0) -> 22.19888 | M14: =M25 -> 24.385607 | N14: =N25 -> 20.611151
A15: Price | B15: ='Data Sheet'!B90 -> 237.46 | C15: ='Data Sheet'!C90 -> 300.09 | D15: ='Data Sheet'!D90 -> 401.08 | E15: ='Data Sheet'!E90 -> 619.43 | F15: ='Data Sheet'!F90 -> 506.06 | G15: ='Data Sheet'!G90 -> 918.78 | H15: ='Data Sheet'!H90 -> 1208.51 | I15: ='Data Sheet'!I90 -> 1069.21 | ... K15: ='Data Sheet'!K90 -> 1275.1 | L15: ='Data Sheet'!B8 -> 1365 | M15: =M13*M14 -> 1462.4723 | N15: =N13*N14 -> 1023.144
A17: RATIOS:
A18: Dividend Payout | B18: =IF('Data Sheet'!B30>0, 'Data Sheet'!B31/'Data Sheet'!B30, 0) -> 0.10406455 | C18: =IF('Data Sheet'!C30>0, 'Data Sheet'!C31/'Data Sheet'!C30, 0) -> 0.10885589 | D18: =IF('Data Sheet'!D30>0, 'Data Sheet'!D31/'Data Sheet'!D30, 0) -> 0.098494802 | E18: =IF('Data Sheet'!E30>0, 'Data Sheet'!E31/'Data Sheet'!E30, 0) -> 0.097299687 | F18: =IF('Data Sheet'!F30>0, 'Data Sheet'!F31/'Data Sheet'!F30, 0) -> 0.10469965 | G18: =IF('Data Sheet'!G30>0, 'Data Sheet'!G31/'Data Sheet'!G30, 0) -> 0.091831542 | H18: =IF('Data Sheet'!H30>0, 'Data Sheet'!H31/'Data Sheet'!H30, 0) -> 0.089152459 | I18: =IF('Data Sheet'!I30>0, 'Data Sheet'!I31/'Data Sheet'!I30, 0) -> 0.091292615 | ... K18: =IF('Data Sheet'!K30>0, 'Data Sheet'!K31/'Data Sheet'!K30, 0) -> 0.10686021
A19: OPM | B19: =IF(B6>0,B6/B4,0) -> 0.15327808 | C19: =IF(C6>0,C6/C4,0) -> 0.15234871 | D19: =IF(D6>0,D6/D4,0) -> 0.16456299 | E19: =IF(E6>0,E6/E4,0) -> 0.14823951 | F19: =IF(F6>0,F6/F4,0) -> 0.14960473 | G19: =IF(G6>0,G6/G4,0) -> 0.17325496 | H19: =IF(H6>0,H6/H4,0) -> 0.1563052 | I19: =IF(I6>0,I6/I4,0) -> 0.16239006 | ... L19: =IF(L6>0,L6/L4,0) -> 0.17435982
G22: TRENDS: | H22: 10 YEARS | I22: 7 YEARS | J22: 5 YEARS | K22: 3 YEARS | L22: RECENT | M22: BEST | N22: WORST
G23: Sales Growth | H23: =IF(B4=0,"",POWER($K4/B4,1/9)-1) -> 0.15051964 | I23: =IF(D4=0,"",POWER($K4/D4,1/7)-1) -> 0.13746451 | J23: =IF(F4=0,"",POWER($K4/F4,1/5)-1) -> 0.10042607 | K23: =IF(H4=0,"",POWER($K4/H4, 1/3)-1) -> 0.11494872 | L23: =IF(ISERROR(MAX(IF(J4=0,"",(K4-J4)/J4),IF(K4=0,"",(L4-K4)/K4))),"",MAX(IF(J4=0,"",(K4-J4)/J4),IF(K4=0,"",(L4-K4)/K4))) -> 0.070941147 | M23: =MAX(K23:L23) -> 0.11494872 | N23: =MIN(H23:L23) -> 0.070941147
G24: OPM | H24: =IF(SUM(B4:$K$4)=0,"",SUMPRODUCT(B19:$K$19,B4:$K$4)/SUM(B4:$K$4)) -> 0.16342295 | I24: =IF(SUM(E4:$K$4)=0,"",SUMPRODUCT(E19:$K$19,E4:$K$4)/SUM(E4:$K$4)) -> 0.16454569 | J24: =IF(SUM(G4:$K$4)=0,"",SUMPRODUCT(G19:$K$19,G4:$K$4)/SUM(G4:$K$4)) -> 0.16920875 | K24: =IF(SUM(I4:$K$4)=0, "", SUMPRODUCT(I19:$K$19,I4:$K$4)/SUM(I4:$K$4)) -> 0.17179322 | L24: =L19 -> 0.17435982 | M24: =MAX(K24:L24) -> 0.17435982 | N24: =MIN(H24:L24) -> 0.16342295
G25: Price to Earning | H25: =IF(ISERROR(AVERAGEIF(B14:$L14,">0")),"",AVERAGEIF(B14:$L14,">0")) -> 20.611151 | I25: =IF(ISERROR(AVERAGEIF(E14:$L14,">0")),"",AVERAGEIF(E14:$L14,">0")) -> 23.342284 | J25: =IF(ISERROR(AVERAGEIF(G14:$L14,">0")),"",AVERAGEIF(G14:$L14,">0")) -> 24.698202 | K25: =IF(ISERROR(AVERAGEIF(I14:$L14,">0")),"",AVERAGEIF(I14:$L14,">0")) -> 24.385607 | L25: =L14 -> 22.19888 | M25: =MAX(K25:L25) -> 24.385607 | N25: =MIN(H25:L25) -> 20.611151

Sheet Quarters
A1: ='Profit & Loss'!A1 -> RELIANCE INDUSTRIES LTD | E1: =UPDATE | J1: SCREENER.IN
A3: Narration | B3: ='Data Sheet'!B41 -> 45199 | C3: ='Data Sheet'!C41 -> 45291 | D3: ='Data Sheet'!D41 -> 45382 | E3: ='Data Sheet'!E41 -> 45473 | F3: ='Data Sheet'!F41 -> 45565 | G3: ='Data Sheet'!G41 -> 45657 | H3: ='Data Sheet'!H41 -> 45747 | I3: ='Data Sheet'!I41 -> 45838 | ... K3: ='Data Sheet'!K41 -> 46022
A4: Sales | B4: ='Data Sheet'!B42 -> 231886 | C4: ='Data Sheet'!C42 -> 225086 | D4: ='Data Sheet'!D42 -> 236533 | E4: ='Data Sheet'!E42 -> 231784 | F4: ='Data Sheet'!F42 -> 231535 | G4: ='Data Sheet'!G42 -> 239986 | H4: ='Data Sheet'!H42 -> 261388 | I4: ='Data Sheet'!I42 -> 243632 | ... K4: ='Data Sheet'!K42 -> 264905
A5: Expenses | B5: ='Data Sheet'!B43 -> 190918 | C5: ='Data Sheet'!C43 -> 184430 | D5: ='Data Sheet'!D43 -> 194017 | E5: ='Data Sheet'!E43 -> 193019 | F5: ='Data Sheet'!F43 -> 192477 | G5: ='Data Sheet'!G43 -> 196197 | H5: ='Data Sheet'!H43 -> 217556 | I5: ='Data Sheet'!I43 -> 200727 | ... K5: ='Data Sheet'!K43 -> 218887
A6: Operating Profit | B6: ='Data Sheet'!B50 -> 40968 | C6: ='Data Sheet'!C50 -> 40656 | D6: ='Data Sheet'!D50 -> 42516 | E6: ='Data Sheet'!E50 -> 38765 | F6: ='Data Sheet'!F50 -> 39058 | G6: ='Data Sheet'!G50 -> 43789 | H6: ='Data Sheet'!H50 -> 43832 | I6: ='Data Sheet'!I50 -> 42905 | ... K6: ='Data Sheet'!K50 -> 46018
A7: Other Income | B7: ='Data Sheet'!B44 -> 3841 | C7: ='Data Sheet'!C44 -> 3869 | D7: ='Data Sheet'!D44 -> 4534 | E7: ='Data Sheet'!E44 -> 3983 | F7: ='Data Sheet'!F44 -> 4876 | G7: ='Data Sheet'!G44 -> 4214 | H7: ='Data Sheet'!H44 -> 4905 | I7: ='Data Sheet'!I44 -> 15119 | ... K7: ='Data Sheet'!K44 -> 4914
A8: Depreciation | B8: ='Data Sheet'!B45 -> 12585 | C8: ='Data Sheet'!C45 -> 12903 | D8: ='Data Sheet'!D45 -> 13569 | E8: ='Data Sheet'!E45 -> 13596 | F8: ='Data Sheet'!F45 -> 12880 | G8: ='Data Sheet'!G45 -> 13181 | H8: ='Data Sheet'!H45 -> 13479 | I8: ='Data Sheet'!I45 -> 13842 | ... K8: ='Data Sheet'!K45 -> 14622
A9: Interest | B9: ='Data Sheet'!B46 -> 5731 | C9: ='Data Sheet'!C46 -> 5789 | D9: ='Data Sheet'!D46 -> 5761 | E9: ='Data Sheet'!E46 -> 5918 | F9: ='Data Sheet'!F46 -> 6017 | G9: ='Data Sheet'!G46 -> 6179 | H9: ='Data Sheet'!H46 -> 6155 | I9: ='Data Sheet'!I46 -> 7036 | ... K9: ='Data Sheet'!K46 -> 6613
A10: Profit before tax | B10: ='Data Sheet'!B47 -> 26493 | C10: ='Data Sheet'!C47 -> 25833 | D10: ='Data Sheet'!D47 -> 27720 | E10: ='Data Sheet'!E47 -> 23234 | F10: ='Data Sheet'!F47 -> 25037 | G10: ='Data Sheet'!G47 -> 28643 | H10: ='Data Sheet'!H47 -> 29103 | I10: ='Data Sheet'!I47 -> 37146 | ... K10: ='Data Sheet'!K47 -> 29697
A11: Tax | B11: ='Data Sheet'!B48 -> 6673 | C11: ='Data Sheet'!C48 -> 6345 | D11: ='Data Sheet'!D48 -> 6577 | E11: ='Data Sheet'!E48 -> 5786 | F11: ='Data Sheet'!F48 -> 5936 | G11: ='Data Sheet'!G48 -> 6839 | H11: ='Data Sheet'!H48 -> 6669 | I11: ='Data Sheet'!I48 -> 6465 | ... K11: ='Data Sheet'!K48 -> 7530
A12: Net profit | B12: ='Data Sheet'!B49 -> 17394 | C12: ='Data Sheet'!C49 -> 17265 | D12: ='Data Sheet'!D49 -> 18951 | E12: ='Data Sheet'!E49 -> 15138 | F12: ='Data Sheet'!F49 -> 16563 | G12: ='Data Sheet'!G49 -> 18540 | H12: ='Data Sheet'!H49 -> 19407 | I12: ='Data Sheet'!I49 -> 26994 | ... K12: ='Data Sheet'!K49 -> 18645
A14: OPM | B14: =IF(B4>0,B6/B4,"") -> 0.17667302 | C14: =IF(C4>0,C6/C4,"") -> 0.18062429 | D14: =IF(D4>0,D6/D4,"") -> 0.17974659 | E14: =IF(E4>0,E6/E4,"") -> 0.16724623 | F14: =IF(F4>0,F6/F4,"") -> 0.16869156 | G14: =IF(G4>0,G6/G4,"") -> 0.18246481 | H14: =IF(H4>0,H6/H4,"") -> 0.16768941 | I14: =IF(I4>0,I6/I4,"") -> 0.17610577 | ... K14: =IF(K4>0,K6/K4,"") -> 0.17371511

Sheet Balance Sheet
A1: ='Profit & Loss'!A1 -> RELIANCE INDUSTRIES LTD | E1: =UPDATE | J1: SCREENER.IN
A3: Narration | B3: ='Data Sheet'!B56 -> 42460 | C3: ='Data Sheet'!C56 -> 42825 | D3: ='Data Sheet'!D56 -> 43190 | E3: ='Data Sheet'!E56 -> 43555 | F3: ='Data Sheet'!F56 -> 43921 | G3: ='Data Sheet'!G56 -> 44286 | H3: ='Data Sheet'!H56 -> 44651 | I3: ='Data Sheet'!I56 -> 45016 | ... K3: ='Data Sheet'!K56 -> 45747
A4: Equity Share Capital | B4: ='Data Sheet'!B57 -> 2948 | C4: ='Data Sheet'!C57 -> 2959 | D4: ='Data Sheet'!D57 -> 5922 | E4: ='Data Sheet'!E57 -> 5926 | F4: ='Data Sheet'!F57 -> 6339 | G4: ='Data Sheet'!G57 -> 6445 | H4: ='Data Sheet'!H57 -> 6765 | I4: ='Data Sheet'!I57 -> 6766 | ... K4: ='Data Sheet'!K57 -> 13532
A5: Reserves | B5: ='Data Sheet'!B58 -> 228608 | C5: ='Data Sheet'!C58 -> 260750 | D5: ='Data Sheet'!D58 -> 287584 | E5: ='Data Sheet'!E58 -> 381186 | F5: ='Data Sheet'!F58 -> 442827 | G5: ='Data Sheet'!G58 -> 693727 | H5: ='Data Sheet'!H58 -> 772720 | I5: ='Data Sheet'!I58 -> 709106 | ... K5: ='Data Sheet'!K58 -> 829668
A6: Borrowings | B6: ='Data Sheet'!B59 -> 194714 | C6: ='Data Sheet'!C59 -> 217475 | D6: ='Data Sheet'!D59 -> 239843 | E6: ='Data Sheet'!E59 -> 307714 | F6: ='Data Sheet'!F59 -> 355133 | G6: ='Data Sheet'!G59 -> 278962 | H6: ='Data Sheet'!H59 -> 319158 | I6: ='Data Sheet'!I59 -> 451664 | ... K6: ='Data Sheet'!K59 -> 374313
A7: Other Liabilities | B7: ='Data Sheet'!B60 -> 172727 | C7: ='Data Sheet'!C60 -> 225618 | D7: ='Data Sheet'!D60 -> 277924 | E7: ='Data Sheet'!E60 -> 302804 | F7: ='Data Sheet'!F60 -> 358716 | G7: ='Data Sheet'!G60 -> 340931 | H7: ='Data Sheet'!H60 -> 399979 | I7: ='Data Sheet'!I60 -> 438346 | ... K7: ='Data Sheet'!K60 -> 732200
A8: Total | B8: ='Data Sheet'!B61 -> 598997 | C8: ='Data Sheet'!C61 -> 706802 | D8: ='Data Sheet'!D61 -> 811273 | E8: ='Data Sheet'!E61 -> 997630 | F8: ='Data Sheet'!F61 -> 1163015 | G8: ='Data Sheet'!G61 -> 1320065 | H8: ='Data Sheet'!H61 -> 1498622 | I8: ='Data Sheet'!I61 -> 1605882 | ... K8: ='Data Sheet'!K61 -> 1949713
A10: Net Block | B10: ='Data Sheet'!B62 -> 184910 | C10: ='Data Sheet'!C62 -> 198526 | D10: ='Data Sheet'!D62 -> 403885 | E10: ='Data Sheet'!E62 -> 398374 | F10: ='Data Sheet'!F62 -> 532658 | G10: ='Data Sheet'!G62 -> 541258 | H10: ='Data Sheet'!H62 -> 627798 | I10: ='Data Sheet'!I62 -> 724805 | ... K10: ='Data Sheet'!K62 -> 999393
A11: Capital Work in Progress | B11: ='Data Sheet'!B63 -> 228697 | C11: ='Data Sheet'!C63 -> 324837 | D11: ='Data Sheet'!D63 -> 187022 | E11: ='Data Sheet'!E63 -> 179463 | F11: ='Data Sheet'!F63 -> 109106 | G11: ='Data Sheet'!G63 -> 125953 | H11: ='Data Sheet'!H63 -> 172506 | I11: ='Data Sheet'!I63 -> 293752 | ... K11: ='Data Sheet'!K63 -> 262358
A12: Investments | B12: ='Data Sheet'!B64 -> 84015 | C12: ='Data Sheet'!C64 -> 82899 | D12: ='Data Sheet'!D64 -> 82862 | E12: ='Data Sheet'!E64 -> 235635 | F12: ='Data Sheet'!F64 -> 276767 | G12: ='Data Sheet'!G64 -> 364828 | H12: ='Data Sheet'!H64 -> 394264 | I12: ='Data Sheet'!I64 -> 235560 | ... K12: ='Data Sheet'!K64 -> 242381
A13: Other Assets | B13: ='Data Sheet'!B65 -> 101375 | C13: ='Data Sheet'!C65 -> 100540 | D13: ='Data Sheet'!D65 -> 137504 | E13: ='Data Sheet'!E65 -> 184158 | F13: ='Data Sheet'!F65 -> 244484 | G13: ='Data Sheet'!G65 -> 288026 | H13: ='Data Sheet'!H65 -> 304054 | I13: ='Data Sheet'!I65 -> 351765 | ... K13: ='Data Sheet'!K65 -> 445581
A14: Total | B14: ='Data Sheet'!B66 -> 598997 | C14: ='Data Sheet'!C66 -> 706802 | D14: ='Data Sheet'!D66 -> 811273 | E14: ='Data Sheet'!E66 -> 997630 | F14: ='Data Sheet'!F66 -> 1163015 | G14: ='Data Sheet'!G66 -> 1320065 | H14: ='Data Sheet'!H66 -> 1498622 | I14: ='Data Sheet'!I66 -> 1605882 | ... K14: ='Data Sheet'!K66 -> 1949713
A16: Working Capital | B16: =B13-B7 -> -71352 | C16: =C13-C7 -> -125078 | D16: =D13-D7 -> -140420 | E16: =E13-E7 -> -118646 | F16: =F13-F7 -> -114232 | G16: =G13-G7 -> -52905 | H16: =H13-H7 -> -95925 | I16: =I13-I7 -> -86581 | ... K16: =K13-K7 -> -286619
A17: Debtors | B17: ='Data Sheet'!B67 -> 4465 | C17: ='Data Sheet'!C67 -> 8177 | D17: ='Data Sheet'!D67 -> 17555 | E17: ='Data Sheet'!E67 -> 30089 | F17: ='Data Sheet'!F67 -> 19656 | G17: ='Data Sheet'!G67 -> 19014 | H17: ='Data Sheet'!H67 -> 23640 | I17: ='Data Sheet'!I67 -> 28448 | ... K17: ='Data Sheet'!K67 -> 42121
A18: Inventory | B18: ='Data Sheet'!B68 -> 46486 | C18: ='Data Sheet'!C68 -> 48951 | D18: ='Data Sheet'!D68 -> 60837 | E18: ='Data Sheet'!E68 -> 67561 | F18: ='Data Sheet'!F68 -> 73903 | G18: ='Data Sheet'!G68 -> 81672 | H18: ='Data Sheet'!H68 -> 107778 | I18: ='Data Sheet'!I68 -> 140008 | ... K18: ='Data Sheet'!K68 -> 146062
A20: Debtor Days | B20: =IF('Profit & Loss'!B4>0,'Balance Sheet'!B17/('Profit & Loss'!B4/365),0) -> 5.9788211 | C20: =IF('Profit & Loss'!C4>0,'Balance Sheet'!C17/('Profit & Loss'!C4/365),0) -> 9.8192654 | D20: =IF('Profit & Loss'!D4>0,'Balance Sheet'!D17/('Profit & Loss'!D4/365),0) -> 16.395082 | E20: =IF('Profit & Loss'!E4>0,'Balance Sheet'!E17/('Profit & Loss'!E4/365),0) -> 19.323896 | F20: =IF('Profit & Loss'!F4>0,'Balance Sheet'!F17/('Profit & Loss'!F4/365),0) -> 12.023953 | G20: =IF('Profit & Loss'!G4>0,'Balance Sheet'!G17/('Profit & Loss'!G4/365),0) -> 14.883135 | H20: =IF('Profit & Loss'!H4>0,'Balance Sheet'!H17/('Profit & Loss'!H4/365),0) -> 12.421096 | I20: =IF('Profit & Loss'!I4>0,'Balance Sheet'!I17/('Profit & Loss'!I4/365),0) -> 11.847977 | ... K20: =IF('Profit & Loss'!K4>0,'Balance Sheet'!K17/('Profit & Loss'!K4/365),0) -> 15.96785
A21: Inventory Turnover | B21: =IF('Balance Sheet'!B18>0,'Profit & Loss'!B4/'Balance Sheet'!B18,0) -> 5.8637654 | C21: =IF('Balance Sheet'!C18>0,'Profit & Loss'!C4/'Balance Sheet'!C18,0) -> 6.2093522 | D21: =IF('Balance Sheet'!D18>0,'Profit & Loss'!D4/'Balance Sheet'!D18,0) -> 6.4241005 | E21: =IF('Balance Sheet'!E18>0,'Profit & Loss'!E4/'Balance Sheet'!E18,0) -> 8.4122053 | F21: =IF('Balance Sheet'!F18>0,'Profit & Loss'!F4/'Balance Sheet'!F18,0) -> 8.073813 | G21: =IF('Balance Sheet'!G18>0,'Profit & Loss'!G4/'Balance Sheet'!G18,0) -> 5.7095088 | H21: =IF('Balance Sheet'!H18>0,'Profit & Loss'!H4/'Balance Sheet'!H18,0) -> 6.4454063 | I21: =IF('Balance Sheet'!I18>0,'Profit & Loss'!I4/'Balance Sheet'!I18,0) -> 6.2596137 | ... K21: =IF('Balance Sheet'!K18>0,'Profit & Loss'!K4/'Balance Sheet'!K18,0) -> 6.5918583
A23: Return on Equity | B23: =IF(SUM('Balance Sheet'!B4:B5)>0,'Profit & Loss'!B12/SUM('Balance Sheet'!B4:B5),"") -> 0.12845705 | C23: =IF(SUM('Balance Sheet'!C4:C5)>0,'Profit & Loss'!C12/SUM('Balance Sheet'!C4:C5),"") -> 0.11338635 | D23: =IF(SUM('Balance Sheet'!D4:D5)>0,'Profit & Loss'!D12/SUM('Balance Sheet'!D4:D5),"") -> 0.1229106 | E23: =IF(SUM('Balance Sheet'!E4:E5)>0,'Profit & Loss'!E12/SUM('Balance Sheet'!E4:E5),"") -> 0.10226498 | F23: =IF(SUM('Balance Sheet'!F4:F5)>0,'Profit & Loss'!F12/SUM('Balance Sheet'!F4:F5),"") -> 0.087615714 | G23: =IF(SUM('Balance Sheet'!G4:G5)>0,'Profit & Loss'!G12/SUM('Balance Sheet'!G4:G5),"") -> 0.070165616 | H23: =IF(SUM('Balance Sheet'!H4:H5)>0,'Profit & Loss'!H12/SUM('Balance Sheet'!H4:H5),"") -> 0.077878343 | I23: =IF(SUM('Balance Sheet'!I4:I5)>0,'Profit & Loss'!I12/SUM('Balance Sheet'!I4:I5),"") -> 0.093175875 | ... K23: =IF(SUM('Balance Sheet'!K4:K5)>0,'Profit & Loss'!K12/SUM('Balance Sheet'!K4:K5),"") -> 0.08259962
A24: Return on Capital Emp | C24: =IF((B4+B5+B6+C4+C5+C6)>0,('Profit & Loss'!C10+'Profit & Loss'!C9)*2/(B4+B5+B6+C4+C5+C6),"") -> 0.096716748 | D24: =IF((C4+C5+C6+D4+D5+D6)>0,('Profit & Loss'!D10+'Profit & Loss'!D9)*2/(C4+C5+C6+D4+D5+D6),"") -> 0.11330928 | E24: =IF((D4+D5+D6+E4+E5+E6)>0,('Profit & Loss'!E10+'Profit & Loss'!E9)*2/(D4+D5+D6+E4+E5+E6),"") -> 0.11679443 | F24: =IF((E4+E5+E6+F4+F5+F6)>0,('Profit & Loss'!F10+'Profit & Loss'!F9)*2/(E4+E5+E6+F4+F5+F6),"") -> 0.10090286 | G24: =IF((F4+F5+F6+G4+G5+G6)>0,('Profit & Loss'!G10+'Profit & Loss'!G9)*2/(F4+F5+F6+G4+G5+G6),"") -> 0.085957813 | H24: =IF((G4+G5+G6+H4+H5+H6)>0,('Profit & Loss'!H10+'Profit & Loss'!H9)*2/(G4+G5+G6+H4+H5+H6),"") -> 0.09471565 | I24: =IF((H4+H5+H6+I4+I5+I6)>0,('Profit & Loss'!I10+'Profit & Loss'!I9)*2/(H4+H5+H6+I4+I5+I6),"") -> 0.10064077 | J24: =IF((I4+I5+I6+J4+J5+J6)>0,('Profit & Loss'!J10+'Profit & Loss'!J9)*2/(I4+I5+I6+J4+J5+J6),"") -> 0.11027038 | K24: =IF((J4+J5+J6+K4+K5+K6)>0,('Profit & Loss'!K10+'Profit & Loss'!K9)*2/(J4+J5+J6+K4+K5+K6),"") -> 0.11033178

Sheet Cash Flow
A1: ='Balance Sheet'!A1 -> RELIANCE INDUSTRIES LTD | E1: =UPDATE | J1: SCREENER.IN
A3: Narration | B3: ='Data Sheet'!B81 -> 42460 | C3: ='Data Sheet'!C81 -> 42825 | D3: ='Data Sheet'!D81 -> 43190 | E3: ='Data Sheet'!E81 -> 43555 | F3: ='Data Sheet'!F81 -> 43921 | G3: ='Data Sheet'!G81 -> 44286 | H3: ='Data Sheet'!H81 -> 44651 | I3: ='Data Sheet'!I81 -> 45016 | ... K3: ='Data Sheet'!K81 -> 45747
A4: Cash from Operating Activity | B4: ='Data Sheet'!B82 -> 38134 | C4: ='Data Sheet'!C82 -> 49550 | D4: ='Data Sheet'!D82 -> 71459 | E4: ='Data Sheet'!E82 -> 42346 | F4: ='Data Sheet'!F82 -> 94877 | G4: ='Data Sheet'!G82 -> 26958 | H4: ='Data Sheet'!H82 -> 110654 | I4: ='Data Sheet'!I82 -> 115032 | ... K4: ='Data Sheet'!K82 -> 178703
A5: Cash from Investing Activity | B5: ='Data Sheet'!B83 -> -36186 | C5: ='Data Sheet'!C83 -> -66201 | D5: ='Data Sheet'!D83 -> -68192 | E5: ='Data Sheet'!E83 -> -94507 | F5: ='Data Sheet'!F83 -> -72497 | G5: ='Data Sheet'!G83 -> -142385 | H5: ='Data Sheet'!H83 -> -109162 | I5: ='Data Sheet'!I83 -> -93001 | ... K5: ='Data Sheet'!K83 -> -137535
A6: Cash from Financing Activity | B6: ='Data Sheet'!B84 -> -3210 | C6: ='Data Sheet'!C84 -> 8617 | D6: ='Data Sheet'!D84 -> -2001 | E6: ='Data Sheet'!E84 -> 55906 | F6: ='Data Sheet'!F84 -> -2541 | G6: ='Data Sheet'!G84 -> 101904 | H6: ='Data Sheet'!H84 -> 17289 | I6: ='Data Sheet'!I84 -> 10455 | ... K6: ='Data Sheet'!K84 -> -31891
A7: Net Cash Flow | B7: ='Data Sheet'!B85 -> -1262 | C7: ='Data Sheet'!C85 -> -8034 | D7: ='Data Sheet'!D85 -> 1266 | E7: ='Data Sheet'!E85 -> 3745 | F7: ='Data Sheet'!F85 -> 19839 | G7: ='Data Sheet'!G85 -> -13523 | H7: ='Data Sheet'!H85 -> 18781 | I7: ='Data Sheet'!I85 -> 32486 | ... K7: ='Data Sheet'!K85 -> 9277

Sheet Customization
A1: How to use it?
A3: You can customize this workbook as you want.
B4: You can add custom formating, add conditional formating, add your own formulas… do ANYTHING.
B5: Please don't edit the "Data Sheet" only.
A7: After customization, you can upload this back on Screener.
B8: Upload on: | C8: https://www.screener.in/excel/
A10: Download your customized workbooks now onwards.
B11: Now whenever you will "Export to excel" from Screener, it will export your customized file.
A14: TESTING:
B15: This is a testing feature currently.
B16: You can report any formula errors on the worksheet at: support@screener.in

Sheet Data Sheet
A1: COMPANY NAME | B1: RELIANCE INDUSTRIES LTD | E1: =IF(B2<>B3, "A NEW VERSION OF THE WORKSHEET IS AVAILABLE", "")
A2: LATEST VERSION | B2: 2.1 | E2: PLEASE DO NOT MAKE ANY CHANGES TO THIS SHEET
A3: CURRENT VERSION | B3: 2.1
A5: META
A6: Number of shares | B6: =IF(B9>0, B9/B8, 0) -> 1353.2535
A7: Face Value | B7: 10
A8: Current Price | B8: 1365
A9: Market Capitalization | B9: 1847191
A15: PROFIT & LOSS
A16: Report Date | B16: 42460 | C16: 42825 | D16: 43190 | E16: 43555 | F16: 43921 | G16: 44286 | H16: 44651 | I16: 45016 | J16: 45382 | K16: 45747
A17: Sales | B17: 272583 | C17: 303954 | D17: 390823 | E17: 568337 | F17: 596679 | G17: 466307 | H17: 694673 | I17: 876396 | J17: 899041 | K17: 962820
A18: Raw Material Cost | B18: 186254 | C18: 217518 | D18: 276076 | E18: 399167 | F18: 410288 | G18: 301765 | H18: 494449 | I18: 618746 | J18: 590226 | K18: 644813
A19: Change in Inventory | B19: -2560 | C19: 5218 | D19: 8610 | E19: 4680 | F19: 5048 | G19: 9064 | H19: 21457 | I19: 30263 | J19: 4883 | K19: 15124
A20: Power and Fuel | B20: 10741 | C20: 11251 | D20: 14569 | E20: 17029 | F20: 15098 | G20: 13214 | H20: 17902 | I20: 25062 | J20: 22137 | K20: 23823
A21: Other Mfr. Exp | B21: 8272 | C21: 9909 | D21: 9691 | E21: 12198 | F21: 11434 | G21: 7687 | H21: 12174 | I21: 19658 | J21: 18276 | K21: 18358
A22: Employee Cost | B22: 7407 | C22: 8388 | D22: 9523 | E22: 12488 | F22: 14075 | G22: 14817 | H22: 18758 | I22: 24872 | J22: 25679 | K22: 28559
A23: Selling and admin | B23: 18808 | C23: 18520 | D23: 29111 | E23: 50221 | F23: 62622 | G23: 56154 | H23: 63513 | I23: 67369 | J23: 77292 | K23: 88760
A24: Other Expenses | B24: -3240 | C24: -2721 | D24: -3852 | E24: -2336 | F24: -1056 | G24: 944 | H24: 753 | I24: 8634 | J24: 7816 | K24: 8033
A25: Other Income | B25: 12212 | C25: 9222 | D25: 9869 | E25: 8406 | F25: 8570 | G25: 22432 | H25: 19600 | I25: 12020 | J25: 15792 | K25: 17824
A26: Depreciation | B26: 11565 | C26: 11646 | D26: 16706 | E26: 20934 | F26: 22203 | G26: 26572 | H26: 29782 | I26: 40303 | J26: 50832 | K26: 53136
A27: Interest | B27: 3691 | C27: 3849 | D27: 8052 | E27: 16495 | F27: 22027 | G27: 21189 | H27: 14584 | I27: 19571 | J27: 23118 | K27: 24269
... A31: Dividend Amount | B31: 3095.4 | C31: 3254.9 | D31: 3553.2 | E31: 3851.9 | F31: 4120.35 | G31: 4511.5 | H31: 5412 | I31: 6089.4 | J31: 6766 | K31: 7442.6
A40: Quarters
A41: Report Date | B41: 45199 | C41: 45291 | D41: 45382 | E41: 45473 | F41: 45565 | G41: 45657 | H41: 45747 | I41: 45838 | J41: 45930 | K41: 46022
A42: Sales | B42: 231886 | C42: 225086 | D42: 236533 | E42: 231784 | F42: 231535 | G42: 239986 | H42: 261388 | I42: 243632 | J42: 254623 | K42: 264905
A43: Expenses | B43: 190918 | C43: 184430 | D43: 194017 | E43: 193019 | F43: 192477 | G43: 196197 | H43: 217556 | I43: 200727 | J43: 208738 | K43: 218887
A44: Other Income | B44: 3841 | C44: 3869 | D44: 4534 | E44: 3983 | F44: 4876 | G44: 4214 | H44: 4905 | I44: 15119 | J44: 4482 | K44: 4914
A45: Depreciation | B45: 12585 | C45: 12903 | D45: 13569 | E45: 13596 | F45: 12880 | G45: 13181 | H45: 13479 | I45: 13842 | J45: 14416 | K45: 14622
A46: Interest | B46: 5731 | C46: 5789 | D46: 5761 | E46: 5918 | F46: 6017 | G46: 6179 | H46: 6155 | I46: 7036 | J46: 6827 | K46: 6613
A47: Profit before tax | B47: 26493 | C47: 25833 | D47: 27720 | E47: 23234 | F47: 25037 | G47: 28643 | H47: 29103 | I47: 37146 | J47: 29124 | K47: 29697
A48: Tax | B48: 6673 | C48: 6345 | D48: 6577 | E48: 5786 | F48: 5936 | G48: 6839 | H48: 6669 | I48: 6465 | J48: 6978 | K48: 7530
A49: Net profit | B49: 17394 | C49: 17265 | D49: 18951 | E49: 15138 | F49: 16563 | G49: 18540 | H49: 19407 | I49: 26994 | J49: 18165 | K49: 18645
A50: Operating Profit | B50: 40968 | C50: 40656 | D50: 42516 | E50: 38765 | F50: 39058 | G50: 43789 | H50: 43832 | I50: 42905 | J50: 45885 | K50: 46018
A55: BALANCE SHEET
A56: Report Date | B56: 42460 | C56: 42825 | D56: 43190 | E56: 43555 | F56: 43921 | G56: 44286 | H56: 44651 | I56: 45016 | J56: 45382 | K56: 45747
A57: Equity Share Capital | B57: 2948 | C57: 2959 | D57: 5922 | E57: 5926 | F57: 6339 | G57: 6445 | H57: 6765 | I57: 6766 | J57: 6766 | K57: 13532
A58: Reserves | B58: 228608 | C58: 260750 | D58: 287584 | E58: 381186 | F58: 442827 | G58: 693727 | H58: 772720 | I58: 709106 | J58: 786715 | K58: 829668
A59: Borrowings | B59: 194714 | C59: 217475 | D59: 239843 | E59: 307714 | F59: 355133 | G59: 278962 | H59: 319158 | I59: 451664 | J59: 350719 | K59: 374313
A60: Other Liabilities | B60: 172727 | C60: 225618 | D60: 277924 | E60: 302804 | F60: 358716 | G60: 340931 | H60: 399979 | I60: 438346 | J60: 610848 | K60: 732200
A61: Total | B61: 598997 | C61: 706802 | D61: 811273 | E61: 997630 | F61: 1163015 | G61: 1320065 | H61: 1498622 | I61: 1605882 | J61: 1755048 | K61: 1949713
A62: Net Block | B62: 184910 | C62: 198526 | D62: 403885 | E62: 398374 | F62: 532658 | G62: 541258 | H62: 627798 | I62: 724805 | J62: 779985 | K62: 999393
A63: Capital Work in Progress | B63: 228697 | C63: 324837 | D63: 187022 | E63: 179463 | F63: 109106 | G63: 125953 | H63: 172506 | I63: 293752 | J63: 338855 | K63: 262358
A64: Investments | B64: 84015 | C64: 82899 | D64: 82862 | E64: 235635 | F64: 276767 | G64: 364828 | H64: 394264 | I64: 235560 | J64: 225672 | K64: 242381
A65: Other Assets | B65: 101375 | C65: 100540 | D65: 137504 | E65: 184158 | F65: 244484 | G65: 288026 | H65: 304054 | I65: 351765 | J65: 410536 | K65: 445581
A66: Total | B66: 598997 | C66: 706802 | D66: 811273 | E66: 997630 | F66: 1163015 | G66: 1320065 | H66: 1498622 | I66: 1605882 | J66: 1755048 | K66: 1949713
A67: Receivables | B67: 4465 | C67: 8177 | D67: 17555 | E67: 30089 | F67: 19656 | G67: 19014 | H67: 23640 | I67: 28448 | J67: 31628 | K67: 42121
... A70: No. of Equity Shares | B70: 2948021694 | C70: 2958924277 | D70: 5921826196 | E70: 5925868997 | F70: 6338693823 | G70: 6762068814 | H70: 6765994014 | I70: 6766094014 | J70: 6766094014 | K70: 13532515463
A71: New Bonus Shares | D71: 2959863235 | E71: 2959863235 | K71: 6766186449
A72: Face value | B72: 10 | C72: 10 | D72: 10 | E72: 10 | F72: 10 | G72: 10 | H72: 10 | I72: 10 | J72: 10 | K72: 10
A80: CASH FLOW:
A81: Report Date | B81: 42460 | C81: 42825 | D81: 43190 | E81: 43555 | F81: 43921 | G81: 44286 | H81: 44651 | I81: 45016 | J81: 45382 | K81: 45747
A82: Cash from Operating Activity | B82: 38134 | C82: 49550 | D82: 71459 | E82: 42346 | F82: 94877 | G82: 26958 | H82: 110654 | I82: 115032 | J82: 158788 | K82: 178703
A83: Cash from Investing Activity | B83: -36186 | C83: -66201 | D83: -68192 | E83: -94507 | F83: -72497 | G83: -142385 | H83: -109162 | I83: -93001 | J83: -113581 | K83: -137535
A84: Cash from Financing Activity | B84: -3210 | C84: 8617 | D84: -2001 | E84: 55906 | F84: -2541 | G84: 101904 | H84: 17289 | I84: 10455 | J84: -16646 | K84: -31891
A85: Net Cash Flow | B85: -1262 | C85: -8034 | D85: 1266 | E85: 3745 | F85: 19839 | G85: -13523 | H85: 18781 | I85: 32486 | J85: 28561 | K85: 9277
A90: PRICE: | B90: 237.46 | C90: 300.09 | D90: 401.08 | E90: 619.43 | F90: 506.06 | G90: 918.78 | H90: 1208.51 | I90: 1069.21 | J90: 1485.85 | K90: 1275.1
A92: DERIVED:
A93: Adjusted Equity Shares in Cr | B93: 1382.58 | C93: 1387.22 | D93: 1351.39 | E93: 1352.26 | F93: 1352.37 | G93: 1267.89 | H93: 1352.98 | I93: 1353.12 | J93: 1353.14 | K93: 1353.24
